[{"namaKab":"SAMBAS","originalFilename":"1_1.jpg","namaPartai":"Partai Kebangkitan Bangsa","id":152257,"noUrut":1,"nama":"ERWIN JOHANA, S.H","stringJenisKelamin":"Laki-Laki"},{"namaKab":"SAMBAS","originalFilename":"1_2.jpg","namaPartai":"Partai Kebangkitan Bangsa","id":160092,"noUrut":2,"nama":"FU JUNG KHIN","stringJenisKelamin":"Laki-Laki"},{"namaKab":"SAMBAS","originalFilename":"1_3.jpg","namaPartai":"Partai Kebangkitan Bangsa","id":160633,"noUrut":3,"nama":"TRISNAWATI, S.Sos","stringJenisKelamin":"Perempuan"},{"namaKab":"SAMBAS","originalFilename":"1_4.jpg","namaPartai":"Partai Kebangkitan Bangsa","id":160580,"noUrut":4,"nama":"NOUR FAZRIN AFRIANI","stringJenisKelamin":"Laki-Laki"},{"namaKab":"SAMBAS","originalFilename":"1_5.jpg","namaPartai":"Partai Kebangkitan Bangsa","id":200077,"noUrut":5,"nama":"MARIANO","stringJenisKelamin":"Laki-Laki"},{"namaKab":"SAMBAS","originalFilename":"1_6.jpg","namaPartai":"Partai Kebangkitan Bangsa","id":210055,"noUrut":6,"nama":"SEPTI MUHERNAWATI","stringJenisKelamin":"Perempuan"},{"namaKab":"SAMBAS","originalFilename":"1_7.jpg","namaPartai":"Partai Kebangkitan Bangsa","id":160954,"noUrut":7,"nama":"ELVIS HIDAYAT","stringJenisKelamin":"Laki-Laki"},{"namaKab":"SAMBAS","originalFilename":"1_8.jpg","namaPartai":"Partai Kebangkitan Bangsa","id":198534,"noUrut":8,"nama":"IMAM MASKEN","stringJenisKelamin":"Laki-Laki"},{"namaKab":"SAMBAS","originalFilename":"1_9.jpg","namaPartai":"Partai Kebangkitan Bangsa","id":159286,"noUrut":9,"nama":"PRATIWI, S.Pd","stringJenisKelamin":"Perempuan"},{"namaKab":"SAMBAS","originalFilename":"1_10.jpg","namaPartai":"Partai Kebangkitan Bangsa","id":203373,"noUrut":10,"nama":"EKA SUSANTI","stringJenisKelamin":"Perempuan"},{"namaKab":"SAMBAS","originalFilename":"1_11.jpg","namaPartai":"Partai Kebangkitan Bangsa","id":158840,"noUrut":11,"nama":"EDY SYAHWANDY, S.P","stringJenisKelamin":"Laki-Laki"}][{"namaKab":"SAMBAS","originalFilename":"2_1.jpg","namaPartai":"PARTAI GERAKAN INDONESIA RAYA","id":118380,"noUrut":1,"nama":"TJONG TJI HOK, S.Pd. M.Pd.","stringJenisKelamin":"Laki-Laki"},{"namaKab":"SAMBAS","originalFilename":"2_2.jpg","namaPartai":"PARTAI GERAKAN INDONESIA RAYA","id":209552,"noUrut":2,"nama":"HANGTUAH, S.Pd.I., M.A.P","stringJenisKelamin":"Laki-Laki"},{"namaKab":"SAMBAS","originalFilename":"2_3.jpg","namaPartai":"PARTAI GERAKAN INDONESIA RAYA","id":165446,"noUrut":3,"nama":"NURUL ARDILA","stringJenisKelamin":"Perempuan"},{"namaKab":"SAMBAS","originalFilename":"2_4.jpg","namaPartai":"PARTAI GERAKAN INDONESIA RAYA","id":113808,"noUrut":4,"nama":"MUHAMMAD AIDIL RODINI, A.Md.Kep.","stringJenisKelamin":"Laki-Laki"},{"namaKab":"SAMBAS","originalFilename":"2_5.jpg","namaPartai":"PARTAI GERAKAN INDONESIA RAYA","id":52200,"noUrut":5,"nama":"SUWANDI","stringJenisKelamin":"Laki-Laki"},{"namaKab":"SAMBAS","originalFilename":"2_6.jpg","namaPartai":"PARTAI GERAKAN INDONESIA RAYA","id":151939,"noUrut":6,"nama":"FITRIANI","stringJenisKelamin":"Perempuan"},{"namaKab":"SAMBAS","originalFilename":"2_7.jpg","namaPartai":"PARTAI GERAKAN INDONESIA RAYA","id":210864,"noUrut":7,"nama":"EKO KASWELI","stringJenisKelamin":"Laki-Laki"},{"namaKab":"SAMBAS","originalFilename":"2_8.jpg","namaPartai":"PARTAI GERAKAN INDONESIA RAYA","id":220628,"noUrut":8,"nama":"Drs. MATNOH","stringJenisKelamin":"Laki-Laki"},{"namaKab":"SAMBAS","originalFilename":"2_9.jpg","namaPartai":"PARTAI GERAKAN INDONESIA RAYA","id":152068,"noUrut":9,"nama":"VIVIEN MITA ONTARI","stringJenisKelamin":"Perempuan"},{"namaKab":"SAMBAS","originalFilename":"2_10.jpg","namaPartai":"PARTAI GERAKAN INDONESIA RAYA","id":208845,"noUrut":10,"nama":"EVA PUSPA","stringJenisKelamin":"Perempuan"},{"namaKab":"SAMBAS","originalFilename":"2_11.jpg","namaPartai":"PARTAI GERAKAN INDONESIA RAYA","id":109236,"noUrut":11,"nama":"KALTIN, S.Pd","stringJenisKelamin":"Laki-Laki"}][{"namaKab":"SAMBAS","originalFilename":"3_1.jpg","namaPartai":"PARTAI DEMOKRASI INDONESIA PERJUANGAN","id":270245,"noUrut":1,"nama":"ARMANTO, SE","stringJenisKelamin":"Laki-Laki"},{"namaKab":"SAMBAS","originalFilename":"3_2.jpg","namaPartai":"PARTAI DEMOKRASI INDONESIA PERJUANGAN","id":275098,"noUrut":2,"nama":"MUHAMAD SARIF","stringJenisKelamin":"Laki-Laki"},{"namaKab":"KUBU RAYA","originalFilename":"3_3.jpg","namaPartai":"PARTAI DEMOKRASI INDONESIA PERJUANGAN","id":256658,"noUrut":3,"nama":"FINA MARTASELA","stringJenisKelamin":"Perempuan"},{"namaKab":"SAMBAS","originalFilename":"3_4.jpg","namaPartai":"PARTAI DEMOKRASI INDONESIA PERJUANGAN","id":204831,"noUrut":4,"nama":"RISKA MAWARNI, M.Pd","stringJenisKelamin":"Perempuan"},{"namaKab":"SAMBAS","originalFilename":"3_5.jpg","namaPartai":"PARTAI DEMOKRASI INDONESIA PERJUANGAN","id":270902,"noUrut":5,"nama":"MUHAMMAD FAUZI, S.Sos","stringJenisKelamin":"Laki-Laki"},{"namaKab":"SAMBAS","originalFilename":"3_6.jpg","namaPartai":"PARTAI DEMOKRASI INDONESIA PERJUANGAN","id":271458,"noUrut":6,"nama":"SYAHRIANTO","stringJenisKelamin":"Laki-Laki"},{"namaKab":"SAMBAS","originalFilename":"3_7.jpg","namaPartai":"PARTAI DEMOKRASI INDONESIA PERJUANGAN","id":230943,"noUrut":7,"nama":"ALIAN","stringJenisKelamin":"Laki-Laki"},{"namaKab":"KOTA PONTIANAK","originalFilename":"3_8.jpg","namaPartai":"PARTAI DEMOKRASI INDONESIA PERJUANGAN","id":275543,"noUrut":8,"nama":"ADE RIA ANGGRIANI","stringJenisKelamin":"Perempuan"},{"namaKab":"KOTA PONTIANAK","originalFilename":"3_9.jpg","namaPartai":"PARTAI DEMOKRASI INDONESIA PERJUANGAN","id":276016,"noUrut":9,"nama":"HERI","stringJenisKelamin":"Laki-Laki"},{"namaKab":"SAMBAS","originalFilename":"PEBIOLA.jpeg","namaPartai":"PARTAI DEMOKRASI INDONESIA PERJUANGAN","id":299836,"noUrut":10,"nama":"FEBIOLA","stringJenisKelamin":"Perempuan"},{"namaKab":"SAMBAS","originalFilename":"4X6 PHOTO.jpeg","namaPartai":"PARTAI DEMOKRASI INDONESIA PERJUANGAN","id":299704,"noUrut":11,"nama":"HENDRO SUDOMO, S.Kom","stringJenisKelamin":"Laki-Laki"}][{"namaKab":"SAMBAS","originalFilename":"4_1.jpg","namaPartai":"Partai Golongan Karya","id":167767,"noUrut":1,"nama":"Ir. H. ARIFIDIAR, M.H","stringJenisKelamin":"Laki-Laki"},{"namaKab":"SAMBAS","originalFilename":"4_2.jpg","namaPartai":"Partai Golongan Karya","id":56089,"noUrut":2,"nama":"U. FARIDA, SH","stringJenisKelamin":"Perempuan"},{"namaKab":"SAMBAS","originalFilename":"4_3.jpg","namaPartai":"Partai Golongan Karya","id":127290,"noUrut":3,"nama":"CHADARI EKA SAPUTRA","stringJenisKelamin":"Laki-Laki"},{"namaKab":"SAMBAS","originalFilename":"4_4.jpg","namaPartai":"Partai Golongan Karya","id":236151,"noUrut":4,"nama":"NOVITA","stringJenisKelamin":"Perempuan"},{"namaKab":"SAMBAS","originalFilename":"4_5.jpg","namaPartai":"Partai Golongan Karya","id":197377,"noUrut":5,"nama":"M. TAMIMI MURTADHO","stringJenisKelamin":"Laki-Laki"},{"namaKab":"KOTA SINGKAWANG","originalFilename":"4_6.jpg","namaPartai":"Partai Golongan Karya","id":196192,"noUrut":6,"nama":"URAY LASTIA MURNI","stringJenisKelamin":"Perempuan"},{"namaKab":"SAMBAS","originalFilename":"4_7.jpg","namaPartai":"Partai Golongan Karya","id":233733,"noUrut":7,"nama":"ASMADI","stringJenisKelamin":"Laki-Laki"},{"namaKab":"SAMBAS","originalFilename":"4_8.jpg","namaPartai":"Partai Golongan Karya","id":297184,"noUrut":8,"nama":"Drs. HENDRA KASMARA","stringJenisKelamin":"Laki-Laki"},{"namaKab":"SAMBAS","originalFilename":"4_9.jpg","namaPartai":"Partai Golongan Karya","id":234153,"noUrut":9,"nama":"WELLY","stringJenisKelamin":"Laki-Laki"}][{"namaKab":"SAMBAS","originalFilename":"5_1.jpg","namaPartai":"Partai NasDem","id":40116,"noUrut":1,"nama":"MARDIANA","stringJenisKelamin":"Perempuan"},{"namaKab":"SAMBAS","originalFilename":"5_2.jpg","namaPartai":"Partai NasDem","id":40005,"noUrut":2,"nama":"SURIADI","stringJenisKelamin":"Laki-Laki"},{"namaKab":"SAMBAS","originalFilename":"5_3.jpg","namaPartai":"Partai NasDem","id":38261,"noUrut":3,"nama":"HJ. NURMAYA DEWI, SE","stringJenisKelamin":"Perempuan"},{"namaKab":"SAMBAS","originalFilename":"5_4.jpg","namaPartai":"Partai NasDem","id":56849,"noUrut":4,"nama":"IRWAN TRIPUTRA","stringJenisKelamin":"Laki-Laki"},{"namaKab":"KOTA SINGKAWANG","originalFilename":"5_5.jpg","namaPartai":"Partai NasDem","id":40075,"noUrut":5,"nama":"AGUS SOFYAN, S.Sos","stringJenisKelamin":"Laki-Laki"},{"namaKab":"SAMBAS","originalFilename":"5_6.jpg","namaPartai":"Partai NasDem","id":49357,"noUrut":6,"nama":"EMI FITRIA, SE","stringJenisKelamin":"Perempuan"},{"namaKab":"SAMBAS","originalFilename":"5_7.jpg","namaPartai":"Partai NasDem","id":49199,"noUrut":7,"nama":"RABUDI","stringJenisKelamin":"Laki-Laki"},{"namaKab":"SAMBAS","originalFilename":"5_8.jpg","namaPartai":"Partai NasDem","id":40159,"noUrut":8,"nama":"VANIA","stringJenisKelamin":"Perempuan"},{"namaKab":"KOTA SINGKAWANG","originalFilename":"5_9.jpg","namaPartai":"Partai NasDem","id":34922,"noUrut":9,"nama":"ALAN BUDI KUSUMA","stringJenisKelamin":"Laki-Laki"},{"namaKab":"SAMBAS","originalFilename":"5_10.jpg","namaPartai":"Partai NasDem","id":89344,"noUrut":10,"nama":"ANGGRAENI","stringJenisKelamin":"Perempuan"},{"namaKab":"SAMBAS","originalFilename":"5_11.jpg","namaPartai":"Partai NasDem","id":69855,"noUrut":11,"nama":"DINO","stringJenisKelamin":"Laki-Laki"}][{"namaKab":"SAMBAS","originalFilename":"8_1.jpg","namaPartai":"Partai Keadilan Sejahtera","id":102700,"noUrut":1,"nama":"ARPANDI, SP","stringJenisKelamin":"Laki-Laki"},{"namaKab":"SAMBAS","originalFilename":"8_2.jpg","namaPartai":"Partai Keadilan Sejahtera","id":102479,"noUrut":2,"nama":"HJ. ASIAH","stringJenisKelamin":"Perempuan"},{"namaKab":"SAMBAS","originalFilename":"8_3.jpg","namaPartai":"Partai Keadilan Sejahtera","id":153788,"noUrut":3,"nama":"KARMADI","stringJenisKelamin":"Laki-Laki"},{"namaKab":"SAMBAS","originalFilename":"8_4.jpg","namaPartai":"Partai Keadilan Sejahtera","id":145750,"noUrut":4,"nama":"SYAHRUDIN, ST","stringJenisKelamin":"Laki-Laki"},{"namaKab":"SAMBAS","originalFilename":"8_5.jpg","namaPartai":"Partai Keadilan Sejahtera","id":145984,"noUrut":5,"nama":"DALILA, S.Pd","stringJenisKelamin":"Perempuan"},{"namaKab":"SAMBAS","originalFilename":"8_6.jpg","namaPartai":"Partai Keadilan Sejahtera","id":160839,"noUrut":6,"nama":"ARIANDI","stringJenisKelamin":"Laki-Laki"},{"namaKab":"SAMBAS","originalFilename":"8_7.jpg","namaPartai":"Partai Keadilan Sejahtera","id":159303,"noUrut":7,"nama":"ARIFIN USMAN","stringJenisKelamin":"Laki-Laki"},{"namaKab":"SAMBAS","originalFilename":"8_8.jpg","namaPartai":"Partai Keadilan Sejahtera","id":146547,"noUrut":8,"nama":"SUFIAN","stringJenisKelamin":"Laki-Laki"},{"namaKab":"SAMBAS","originalFilename":"8_9.jpg","namaPartai":"Partai Keadilan Sejahtera","id":145620,"noUrut":9,"nama":"LILIS SUHERTI","stringJenisKelamin":"Perempuan"},{"namaKab":"SAMBAS","originalFilename":"8_10.jpg","namaPartai":"Partai Keadilan Sejahtera","id":161417,"noUrut":10,"nama":"DARE","stringJenisKelamin":"Perempuan"},{"namaKab":"SAMBAS","originalFilename":"8_11.jpg","namaPartai":"Partai Keadilan Sejahtera","id":152420,"noUrut":11,"nama":"NAZARUDIN, SP","stringJenisKelamin":"Laki-Laki"}][{"namaKab":"SAMBAS","originalFilename":"HATULISPA.jpg","namaPartai":"Persatuan Indonesia","id":42862,"noUrut":1,"nama":"HATULISPA","stringJenisKelamin":"Laki-Laki"},{"namaKab":"SAMBAS","originalFilename":"SUPIYANTONO.jpg","namaPartai":"Persatuan Indonesia","id":42919,"noUrut":2,"nama":"SUPIYANTONO","stringJenisKelamin":"Laki-Laki"},{"namaKab":"SAMBAS","originalFilename":"DIANA.jpg","namaPartai":"Persatuan Indonesia","id":73618,"noUrut":3,"nama":"DIANA","stringJenisKelamin":"Perempuan"},{"namaKab":"SAMBAS","originalFilename":"BUDIMAN.jpg","namaPartai":"Persatuan Indonesia","id":42828,"noUrut":4,"nama":"BUDIMAN","stringJenisKelamin":"Laki-Laki"},{"namaKab":"SAMBAS","originalFilename":"ENDANG ISMAIL.jpg","namaPartai":"Persatuan Indonesia","id":43867,"noUrut":5,"nama":"ENDANG ISMAIL","stringJenisKelamin":"Laki-Laki"},{"namaKab":"SAMBAS","originalFilename":"DWINDA PRATIWI.jpg","namaPartai":"Persatuan Indonesia","id":73541,"noUrut":6,"nama":"DWINDA PRATIWI","stringJenisKelamin":"Perempuan"},{"namaKab":"SAMBAS","originalFilename":"TEGUH SANJAYA.jpg","namaPartai":"Persatuan Indonesia","id":43790,"noUrut":7,"nama":"TEGUH SANJAYA","stringJenisKelamin":"Laki-Laki"},{"namaKab":"SAMBAS","originalFilename":"MARIANI.jpg","namaPartai":"Persatuan Indonesia","id":73460,"noUrut":8,"nama":"MARIANI","stringJenisKelamin":"Perempuan"},{"namaKab":"SAMBAS","originalFilename":"JEFRI,SP.jpg","namaPartai":"Persatuan Indonesia","id":42653,"noUrut":9,"nama":"JEFRI, S.P","stringJenisKelamin":"Laki-Laki"},{"namaKab":"SAMBAS","originalFilename":"SUKRIADI.jpg","namaPartai":"Persatuan Indonesia","id":43971,"noUrut":10,"nama":"SUKRIADI","stringJenisKelamin":"Laki-Laki"}][{"namaKab":"SAMBAS","originalFilename":"10_1.jpg","namaPartai":"Partai Persatuan pembangunan","id":113081,"noUrut":1,"nama":"MURTANI","stringJenisKelamin":"Laki-Laki"},{"namaKab":"SAMBAS","originalFilename":"10_2.jpg","namaPartai":"Partai Persatuan pembangunan","id":129442,"noUrut":2,"nama":"JUMADI","stringJenisKelamin":"Laki-Laki"},{"namaKab":"SAMBAS","originalFilename":"10_3.jpg","namaPartai":"Partai Persatuan pembangunan","id":112935,"noUrut":3,"nama":"EVI SISCARA PUTRI, S.Pd","stringJenisKelamin":"Perempuan"},{"namaKab":"SAMBAS","originalFilename":"10_4.jpg","namaPartai":"Partai Persatuan pembangunan","id":213391,"noUrut":4,"nama":"SYAMSI","stringJenisKelamin":"Laki-Laki"},{"namaKab":"SAMBAS","originalFilename":"10_5.jpg","namaPartai":"Partai Persatuan pembangunan","id":129150,"noUrut":5,"nama":"SUKARNI","stringJenisKelamin":"Laki-Laki"},{"namaKab":"SAMBAS","originalFilename":"10_6.jpg","namaPartai":"Partai Persatuan pembangunan","id":215897,"noUrut":6,"nama":"EARLIE RUSMANA","stringJenisKelamin":"Perempuan"},{"namaKab":"SAMBAS","originalFilename":"10_7.jpg","namaPartai":"Partai Persatuan pembangunan","id":129720,"noUrut":7,"nama":"ASNANDI, A.Md","stringJenisKelamin":"Laki-Laki"},{"namaKab":"SAMBAS","originalFilename":"10_8.jpg","namaPartai":"Partai Persatuan pembangunan","id":129849,"noUrut":8,"nama":"DEWI HERTIKA","stringJenisKelamin":"Perempuan"},{"namaKab":"SAMBAS","originalFilename":"10_9.jpg","namaPartai":"Partai Persatuan pembangunan","id":127434,"noUrut":9,"nama":"JURAIDA","stringJenisKelamin":"Perempuan"},{"namaKab":"SAMBAS","originalFilename":"10_10.jpg","namaPartai":"Partai Persatuan pembangunan","id":129318,"noUrut":10,"nama":"IVANDRI, SE, MH","stringJenisKelamin":"Laki-Laki"},{"namaKab":"SAMBAS","originalFilename":"10_11.jpg","namaPartai":"Partai Persatuan pembangunan","id":216283,"noUrut":11,"nama":"WELLY SUWANDI","stringJenisKelamin":"Laki-Laki"}][{"namaKab":"SAMBAS","originalFilename":"12_1.jpeg","namaPartai":"PARTAI AMANAT NASIONAL","id":72766,"noUrut":1,"nama":"DEDI SUHENDY, A.Md","stringJenisKelamin":"Laki-Laki"},{"namaKab":"SAMBAS","originalFilename":"12_2.jpg","namaPartai":"PARTAI AMANAT NASIONAL","id":72575,"noUrut":2,"nama":"AWANG AKHSAN","stringJenisKelamin":"Laki-Laki"},{"namaKab":"SAMBAS","originalFilename":"12_3.jpg","namaPartai":"PARTAI AMANAT NASIONAL","id":72508,"noUrut":3,"nama":"NURUL FRIDA ASTUTI","stringJenisKelamin":"Perempuan"},{"namaKab":"SAMBAS","originalFilename":"12_4.jpg","namaPartai":"PARTAI AMANAT NASIONAL","id":72432,"noUrut":4,"nama":"YATIMANSYAH","stringJenisKelamin":"Laki-Laki"},{"namaKab":"SAMBAS","originalFilename":"12_5.jpg","namaPartai":"PARTAI AMANAT NASIONAL","id":72200,"noUrut":5,"nama":"JUNIARDI","stringJenisKelamin":"Laki-Laki"},{"namaKab":"SAMBAS","originalFilename":"12_6.jpg","namaPartai":"PARTAI AMANAT NASIONAL","id":72098,"noUrut":6,"nama":"MEGAWATI","stringJenisKelamin":"Perempuan"},{"namaKab":"SAMBAS","originalFilename":"12_7.jpg","namaPartai":"PARTAI AMANAT NASIONAL","id":72171,"noUrut":7,"nama":"TRISNO","stringJenisKelamin":"Laki-Laki"},{"namaKab":"SAMBAS","originalFilename":"12_8.jpg","namaPartai":"PARTAI AMANAT NASIONAL","id":72703,"noUrut":8,"nama":"WILMA","stringJenisKelamin":"Perempuan"},{"namaKab":"SAMBAS","originalFilename":"12_9.jpg","namaPartai":"PARTAI AMANAT NASIONAL","id":72132,"noUrut":9,"nama":"H. RAHMAT H. JUHDI","stringJenisKelamin":"Laki-Laki"},{"namaKab":"SAMBAS","originalFilename":"12_10.jpg","namaPartai":"PARTAI AMANAT NASIONAL","id":72078,"noUrut":10,"nama":"HUDZAIFAH","stringJenisKelamin":"Perempuan"},{"namaKab":"SAMBAS","originalFilename":"12_11.jpg","namaPartai":"PARTAI AMANAT NASIONAL","id":72111,"noUrut":11,"nama":"URAY EGIE PRUZIA RINALDI, A.Md","stringJenisKelamin":"Laki-Laki"}][{"namaKab":"SAMBAS","originalFilename":"13_1.jpg","namaPartai":"Partai Hati Nurani Rakyat","id":47698,"noUrut":1,"nama":"H. BADRI KODRI","stringJenisKelamin":"Laki-Laki"},{"namaKab":"SAMBAS","originalFilename":"13_2.jpg","namaPartai":"Partai Hati Nurani Rakyat","id":47661,"noUrut":2,"nama":"HADIYANTO","stringJenisKelamin":"Laki-Laki"},{"namaKab":"SAMBAS","originalFilename":"13_3.jpg","namaPartai":"Partai Hati Nurani Rakyat","id":47735,"noUrut":3,"nama":"ABDIAH","stringJenisKelamin":"Perempuan"},{"namaKab":"KOTA PONTIANAK","originalFilename":"13_4.jpg","namaPartai":"Partai Hati Nurani Rakyat","id":47678,"noUrut":4,"nama":"HARI ARDIAN","stringJenisKelamin":"Laki-Laki"},{"namaKab":"SAMBAS","originalFilename":"13_5.jpg","namaPartai":"Partai Hati Nurani Rakyat","id":47755,"noUrut":5,"nama":"USMANTO","stringJenisKelamin":"Laki-Laki"},{"namaKab":"SAMBAS","originalFilename":"13_6.jpg","namaPartai":"Partai Hati Nurani Rakyat","id":47753,"noUrut":6,"nama":"MERKI BOHITA","stringJenisKelamin":"Perempuan"},{"namaKab":"SAMBAS","originalFilename":"13_7.jpg","namaPartai":"Partai Hati Nurani Rakyat","id":47722,"noUrut":7,"nama":"GIFFARIAN, S.Sos","stringJenisKelamin":"Laki-Laki"},{"namaKab":"SAMBAS","originalFilename":"13_8.jpg","namaPartai":"Partai Hati Nurani Rakyat","id":47741,"noUrut":8,"nama":"TJHIE TJIE KHIAN","stringJenisKelamin":"Laki-Laki"},{"namaKab":"SAMBAS","originalFilename":"13_9.jpg","namaPartai":"Partai Hati Nurani Rakyat","id":47729,"noUrut":9,"nama":"MEGAWATI","stringJenisKelamin":"Perempuan"},{"namaKab":"SAMBAS","originalFilename":"13_10.jpg","namaPartai":"Partai Hati Nurani Rakyat","id":47748,"noUrut":10,"nama":"SRI WAHYUNI","stringJenisKelamin":"Perempuan"},{"namaKab":"SAMBAS","originalFilename":"13_11.jpg","namaPartai":"Partai Hati Nurani Rakyat","id":47711,"noUrut":11,"nama":"ASWANDI, SH","stringJenisKelamin":"Laki-Laki"}][{"namaKab":"SAMBAS","originalFilename":"14_1.jpg","namaPartai":"PARTAI DEMOKRAT","id":103686,"noUrut":1,"nama":"EDIANTO","stringJenisKelamin":"Laki-Laki"},{"namaKab":"SAMBAS","originalFilename":"14_2.jpg","namaPartai":"PARTAI DEMOKRAT","id":103725,"noUrut":2,"nama":"ALFIAN","stringJenisKelamin":"Laki-Laki"},{"namaKab":"SAMBAS","originalFilename":"14_3.jpg","namaPartai":"PARTAI DEMOKRAT","id":103770,"noUrut":3,"nama":"NURHAYATI","stringJenisKelamin":"Perempuan"},{"namaKab":"SAMBAS","originalFilename":"14_4.jpg","namaPartai":"PARTAI DEMOKRAT","id":103843,"noUrut":4,"nama":"PAISAL HAZIM","stringJenisKelamin":"Laki-Laki"},{"namaKab":"KOTA SINGKAWANG","originalFilename":"14_5.jpg","namaPartai":"PARTAI DEMOKRAT","id":103879,"noUrut":5,"nama":"RAJU VERNANDO","stringJenisKelamin":"Laki-Laki"},{"namaKab":"SAMBAS","originalFilename":"14_6.jpg","namaPartai":"PARTAI DEMOKRAT","id":103923,"noUrut":6,"nama":"NURUL ARESTI","stringJenisKelamin":"Perempuan"},{"namaKab":"SAMBAS","originalFilename":"14_7.jpg","namaPartai":"PARTAI DEMOKRAT","id":103971,"noUrut":7,"nama":"MUZAHAR","stringJenisKelamin":"Laki-Laki"},{"namaKab":"SAMBAS","originalFilename":"14_8.jpg","namaPartai":"PARTAI DEMOKRAT","id":106766,"noUrut":8,"nama":"SAMIRI","stringJenisKelamin":"Laki-Laki"},{"namaKab":"SAMBAS","originalFilename":"14_9.jpg","namaPartai":"PARTAI DEMOKRAT","id":105247,"noUrut":9,"nama":"SURIANTI","stringJenisKelamin":"Perempuan"},{"namaKab":"SAMBAS","originalFilename":"14_10.jpg","namaPartai":"PARTAI DEMOKRAT","id":106798,"noUrut":10,"nama":"DEDI PURWANTO","stringJenisKelamin":"Laki-Laki"},{"namaKab":"SAMBAS","originalFilename":"14_11.jpg","namaPartai":"PARTAI DEMOKRAT","id":105295,"noUrut":11,"nama":"GUSDAFIA","stringJenisKelamin":"Perempuan"}][{"namaKab":"SAMBAS","originalFilename":"1. RUSLAN.jpg","namaPartai":"Partai Bulan Bintang","id":73607,"noUrut":1,"nama":"RUSLAN","stringJenisKelamin":"Laki-Laki"},{"namaKab":"SAMBAS","originalFilename":"2. NORHAN.jpg","namaPartai":"Partai Bulan Bintang","id":73727,"noUrut":2,"nama":"NORHAN","stringJenisKelamin":"Laki-Laki"},{"namaKab":"SAMBAS","originalFilename":"WIWIN SUNARSIH, S.Pd.jpg","namaPartai":"Partai Bulan Bintang","id":292652,"noUrut":3,"nama":"WIWIN SUNARSIH, S.Pd","stringJenisKelamin":"Perempuan"},{"namaKab":"SAMBAS","originalFilename":"4. SUMADI.jpg","namaPartai":"Partai Bulan Bintang","id":276055,"noUrut":4,"nama":"SUMADI","stringJenisKelamin":"Laki-Laki"},{"namaKab":"SAMBAS","originalFilename":"5. M. RIDWAN.jpg","namaPartai":"Partai Bulan Bintang","id":201920,"noUrut":5,"nama":"MUHAMMAD RIDWAN","stringJenisKelamin":"Laki-Laki"},{"namaKab":"SAMBAS","originalFilename":"6. U SUKMAWATI.jpg","namaPartai":"Partai Bulan Bintang","id":203592,"noUrut":6,"nama":"U. SUKMAWATI","stringJenisKelamin":"Perempuan"},{"namaKab":"SAMBAS","originalFilename":"7. CICI ASTUTI.jpg","namaPartai":"Partai Bulan Bintang","id":204302,"noUrut":7,"nama":"CICI ASTUTI","stringJenisKelamin":"Perempuan"},{"namaKab":"SAMBAS","originalFilename":"9. SUBAGIO HR.jpg","namaPartai":"Partai Bulan Bintang","id":79960,"noUrut":8,"nama":"SUBAGIO HR","stringJenisKelamin":"Laki-Laki"}][{"namaKab":"SAMBAS","originalFilename":"20_1.jpg","namaPartai":"Partai Keadilan dan Persatuan Indonesia","id":264865,"noUrut":1,"nama":"DARJO ASMAJA","stringJenisKelamin":"Laki-Laki"},{"namaKab":"SAMBAS","originalFilename":"20_2.jpg","namaPartai":"Partai Keadilan dan Persatuan Indonesia","id":178296,"noUrut":2,"nama":"DESY PURWANTI","stringJenisKelamin":"Perempuan"},{"namaKab":"SAMBAS","originalFilename":"20_3.jpg","namaPartai":"Partai Keadilan dan Persatuan Indonesia","id":178087,"noUrut":3,"nama":"DENY SAPUTRA, ST","stringJenisKelamin":"Laki-Laki"}]