[{"namaKab":"KOTA BEKASI","originalFilename":"4 hilman joyo saputra foto_1.jpg","namaPartai":"Partai Kebangkitan Bangsa","id":135021,"noUrut":1,"nama":"HILMAN JOYO SAPUTRA","stringJenisKelamin":"Laki-Laki"},{"namaKab":"KOTA BEKASI","originalFilename":"4 ade sera foto_1.jpg","namaPartai":"Partai Kebangkitan Bangsa","id":196478,"noUrut":2,"nama":"ADE SERA MULYANA","stringJenisKelamin":"Perempuan"},{"namaKab":"KOTA BEKASI","originalFilename":"4 syamsul arifin foto_1.jpg","namaPartai":"Partai Kebangkitan Bangsa","id":119031,"noUrut":3,"nama":"SYAMSUL ARIFIN","stringJenisKelamin":"Laki-Laki"},{"namaKab":"KOTA BEKASI","originalFilename":"4 M. MISBAH FOTO.jpg","namaPartai":"Partai Kebangkitan Bangsa","id":217599,"noUrut":4,"nama":"MUHAMAD MISBAH","stringJenisKelamin":"Laki-Laki"},{"namaKab":"KOTA BEKASI","namaPartai":"Partai Kebangkitan Bangsa","id":305285,"noUrut":5,"nama":"ASIH YUNIARSIH","stringJenisKelamin":"Perempuan"},{"namaKab":"KOTA BEKASI","originalFilename":"FOTO.jpg","namaPartai":"Partai Kebangkitan Bangsa","id":243482,"noUrut":6,"nama":"MUHAMMAD","stringJenisKelamin":"Laki-Laki"},{"namaKab":"KOTA BEKASI","originalFilename":"4 titin foto_1.jpg","namaPartai":"Partai Kebangkitan Bangsa","id":282748,"noUrut":7,"nama":"TITIN AGUSTIN","stringJenisKelamin":"Perempuan"}][{"namaKab":"KOTA BEKASI","originalFilename":"IMG_20180715_0001.jpg","namaPartai":"PARTAI GERAKAN INDONESIA RAYA","id":219463,"noUrut":1,"nama":"SUPANDI, SE","stringJenisKelamin":"Laki-Laki"},{"namaKab":"KOTA BEKASI","originalFilename":"IMG_20180714_0001.jpg","namaPartai":"PARTAI GERAKAN INDONESIA RAYA","id":178984,"noUrut":2,"nama":"YADI HIDAYAT, SIP","stringJenisKelamin":"Laki-Laki"},{"namaKab":"BEKASI","originalFilename":"IMG_20180716_0003.jpg","namaPartai":"PARTAI GERAKAN INDONESIA RAYA","id":221992,"noUrut":3,"nama":"YENNI KHAIDIR","stringJenisKelamin":"Perempuan"},{"namaKab":"KOTA BEKASI","originalFilename":"Foto.jpg","namaPartai":"PARTAI GERAKAN INDONESIA RAYA","id":244896,"noUrut":4,"nama":"H. AHMAD JAYADIH","stringJenisKelamin":"Laki-Laki"},{"namaKab":"KOTA BEKASI","originalFilename":"IMG_20180715_0001.jpg","namaPartai":"PARTAI GERAKAN INDONESIA RAYA","id":220285,"noUrut":5,"nama":"BETTY SETIANINGSIH","stringJenisKelamin":"Perempuan"},{"namaKab":"KOTA BEKASI","originalFilename":"IMG_20180715_0002.jpg","namaPartai":"PARTAI GERAKAN INDONESIA RAYA","id":221309,"noUrut":6,"nama":"JURIKE ADJU","stringJenisKelamin":"Perempuan"},{"namaKab":"KOTA BEKASI","originalFilename":"4 X 6 1.jpg","namaPartai":"PARTAI GERAKAN INDONESIA RAYA","id":144230,"noUrut":7,"nama":"FERDINAND BILLY","stringJenisKelamin":"Laki-Laki"}][{"namaKab":"KOTA BEKASI","originalFilename":"1. ANIM IMAMUDDIN.jpg","namaPartai":"PARTAI DEMOKRASI INDONESIA PERJUANGAN","id":79787,"noUrut":1,"nama":"ANIM IMAMUDDIN, S.E,M.M","stringJenisKelamin":"Laki-Laki"},{"namaKab":"KOTA BEKASI","originalFilename":"2. SRI MASTUTI.jpg","namaPartai":"PARTAI DEMOKRASI INDONESIA PERJUANGAN","id":173017,"noUrut":2,"nama":"SRIMASTUTI, S.IP","stringJenisKelamin":"Perempuan"},{"namaKab":"KOTA BEKASI","originalFilename":"3. ASAN.jpg","namaPartai":"PARTAI DEMOKRASI INDONESIA PERJUANGAN","id":86605,"noUrut":3,"nama":"ASAN, ST.Pnb","stringJenisKelamin":"Laki-Laki"},{"namaKab":"KOTA BEKASI","originalFilename":"4. AGUS.jpeg","namaPartai":"PARTAI DEMOKRASI INDONESIA PERJUANGAN","id":86626,"noUrut":4,"nama":"AGUS","stringJenisKelamin":"Laki-Laki"},{"namaKab":"KOTA BEKASI","originalFilename":"5. MELVA MELANIA.jpeg","namaPartai":"PARTAI DEMOKRASI INDONESIA PERJUANGAN","id":86695,"noUrut":5,"nama":"MELVA MELANIA SIHOMBING","stringJenisKelamin":"Perempuan"},{"namaKab":"KOTA BEKASI","originalFilename":"6. WALTER FRANSISKUS.jpg","namaPartai":"PARTAI DEMOKRASI INDONESIA PERJUANGAN","id":233559,"noUrut":6,"nama":"WALTER FRANSISKUS, S.Sos","stringJenisKelamin":"Laki-Laki"},{"namaKab":"KOTA BEKASI","originalFilename":"7. BETRIZA RIKA.jpg","namaPartai":"PARTAI DEMOKRASI INDONESIA PERJUANGAN","id":86642,"noUrut":7,"nama":"BETRIZA RIKA, S.KOM","stringJenisKelamin":"Perempuan"}][{"namaKab":"KOTA BEKASI","originalFilename":"1. ARDIN MARHAM.jpg","namaPartai":"Partai Golongan Karya","id":261600,"noUrut":1,"nama":"ARDIN MARHAM","stringJenisKelamin":"Laki-Laki"},{"namaKab":"KOTA BEKASI","originalFilename":"2. H. EDI.jpg","namaPartai":"Partai Golongan Karya","id":261224,"noUrut":2,"nama":"H. EDI, S.Sos.I","stringJenisKelamin":"Laki-Laki"},{"namaKab":"KOTA BEKASI","originalFilename":"3. HJ RESTI.jpg","namaPartai":"Partai Golongan Karya","id":260987,"noUrut":3,"nama":"RESTI WINDARTI, S.H","stringJenisKelamin":"Perempuan"},{"namaKab":"KOTA BEKASI","originalFilename":"4. KARYA AHMAD.jpg","namaPartai":"Partai Golongan Karya","id":261104,"noUrut":4,"nama":"KARYA AHMAD","stringJenisKelamin":"Laki-Laki"},{"namaKab":"KOTA BEKASI","originalFilename":"5. MUSTOPA.jpg","namaPartai":"Partai Golongan Karya","id":260807,"noUrut":5,"nama":"MUSTOPA KARYANA, S.E","stringJenisKelamin":"Laki-Laki"},{"namaKab":"KOTA BEKASI","originalFilename":"6. ASTRID WULANDARI.jpg","namaPartai":"Partai Golongan Karya","id":260697,"noUrut":6,"nama":"ASTRID WULANDARI","stringJenisKelamin":"Perempuan"},{"namaKab":"KOTA BEKASI","originalFilename":"7. KELLY.jpg","namaPartai":"Partai Golongan Karya","id":260589,"noUrut":7,"nama":"THELLY KELLY THERESIA","stringJenisKelamin":"Perempuan"}][{"namaKab":"KOTA BEKASI","originalFilename":"pas foto putih.jpg","namaPartai":"Partai NasDem","id":188689,"noUrut":1,"nama":"Hj. RINA GUSPITASARI","stringJenisKelamin":"Perempuan"},{"namaKab":"KOTA BEKASI","originalFilename":"FOTO IBU ELLYA.jpg","namaPartai":"Partai NasDem","id":189477,"noUrut":2,"nama":"Hj. ELLYA TRISKOVA, SE","stringJenisKelamin":"Perempuan"},{"namaKab":"KOTA BEKASI","originalFilename":"FOTO.jpg","namaPartai":"Partai NasDem","id":189735,"noUrut":3,"nama":"IKHSAN HADI PRASETYO, M.PD","stringJenisKelamin":"Laki-Laki"},{"namaKab":"KOTA BEKASI","originalFilename":"bpk nasdem.jpg","namaPartai":"Partai NasDem","id":189624,"noUrut":4,"nama":"MAWI HERMAWAN, AMK","stringJenisKelamin":"Laki-Laki"},{"namaKab":"KOTA BEKASI","originalFilename":"WhatsApp Image 2018-07-12 at 23.28.44.jpeg","namaPartai":"Partai NasDem","id":189132,"noUrut":5,"nama":"Hj. MANGGAR PRATOLOWATI","stringJenisKelamin":"Perempuan"},{"namaKab":"KOTA BEKASI","originalFilename":"PAS FOTO.jpg","namaPartai":"Partai NasDem","id":187343,"noUrut":6,"nama":"NAMAN KOESUMARDANI EJ, SE","stringJenisKelamin":"Laki-Laki"},{"namaKab":"KOTA BEKASI","originalFilename":"11.jpg","namaPartai":"Partai NasDem","id":188952,"noUrut":7,"nama":"REVOLITA RIZAL, A.md","stringJenisKelamin":"Laki-Laki"}][{"namaKab":"KOTA BEKASI","originalFilename":"foto.jpg","namaPartai":"Partai Gerakan Perubahan Indonesia","id":47415,"noUrut":1,"nama":"ZENY NURZAMAN ZEIN","stringJenisKelamin":"Laki-Laki"},{"namaKab":"KOTA BEKASI","originalFilename":"FOTO.jpg","namaPartai":"Partai Gerakan Perubahan Indonesia","id":47282,"noUrut":2,"nama":"DODY YUDHA M. R","stringJenisKelamin":"Laki-Laki"},{"namaKab":"KOTA BEKASI","originalFilename":"FOTO.jpg","namaPartai":"Partai Gerakan Perubahan Indonesia","id":124062,"noUrut":3,"nama":"ERTAWATI TARIGAN","stringJenisKelamin":"Perempuan"},{"namaKab":"JAKARTA TIMUR","originalFilename":"foto.jpg","namaPartai":"Partai Gerakan Perubahan Indonesia","id":210906,"noUrut":4,"nama":"RISMA SETYARINI, SH","stringJenisKelamin":"Perempuan"},{"namaKab":"KOTA BEKASI","originalFilename":"FOTO.jpg","namaPartai":"Partai Gerakan Perubahan Indonesia","id":71739,"noUrut":5,"nama":"UNTUNG LAKSONO","stringJenisKelamin":"Laki-Laki"}][{"namaKab":"KOTA BEKASI","originalFilename":"Dapil 4 - No.Urut 1 - Misan Heryanto.jpg","namaPartai":"PARTAI BERKARYA","id":269279,"noUrut":1,"nama":"MISAN HERYANTO","stringJenisKelamin":"Laki-Laki"},{"namaKab":"KOTA BEKASI","originalFilename":"Dapil 4 - No.Urut 2 - Ida Farida.jpg","namaPartai":"PARTAI BERKARYA","id":269703,"noUrut":2,"nama":"IDA FARIDA","stringJenisKelamin":"Perempuan"},{"namaKab":"KOTA BEKASI","originalFilename":"PHOTO joko widodo(Dapil4).jpg","namaPartai":"PARTAI BERKARYA","id":270007,"noUrut":3,"nama":"DJOKO WIDODO","stringJenisKelamin":"Laki-Laki"},{"namaKab":"KOTA BEKASI","originalFilename":"Dapil 4 - No.Urut 4 - Dewi Yulianty.jpg","namaPartai":"PARTAI BERKARYA","id":270509,"noUrut":4,"nama":"DEWI YULIANTY","stringJenisKelamin":"Perempuan"},{"namaKab":"KOTA BEKASI","originalFilename":"Dapil 4 - No.Urut 5 - Situmeang.jpg","namaPartai":"PARTAI BERKARYA","id":271411,"noUrut":5,"nama":"SITUMEANG PBH","stringJenisKelamin":"Laki-Laki"},{"namaKab":"KOTA BEKASI","originalFilename":"Dapil 4 - No.Urut 7 - Bambang Widiarto SE.jpg","namaPartai":"PARTAI BERKARYA","id":272450,"noUrut":6,"nama":"BAMBANG WIDIARTO, SE","stringJenisKelamin":"Laki-Laki"},{"namaKab":"KOTA BEKASI","originalFilename":"Dapil 4 - No.Urut 6 - Widyawati Farah Imelda.jpg","namaPartai":"PARTAI BERKARYA","id":271956,"noUrut":7,"nama":"WIDYAWATI FARAH IMELDA, SE","stringJenisKelamin":"Perempuan"}][{"namaKab":"KOTA BEKASI","originalFilename":"0401PKS_Ir H DARADJAT KARDONO.jpg","namaPartai":"Partai Keadilan Sejahtera","id":165704,"noUrut":1,"nama":"Ir. H. DARADJAT KARDONO","stringJenisKelamin":"Laki-Laki"},{"namaKab":"KOTA BEKASI","originalFilename":"0402PKS_SUTRIS.jpg","namaPartai":"Partai Keadilan Sejahtera","id":191090,"noUrut":2,"nama":"SUTRIS, SE","stringJenisKelamin":"Laki-Laki"},{"namaKab":"KOTA BEKASI","originalFilename":"0403PKS_PUSPA PERMASWARI.jpg","namaPartai":"Partai Keadilan Sejahtera","id":187584,"noUrut":3,"nama":"PUSPA PERMASWARI, A.Md","stringJenisKelamin":"Perempuan"},{"namaKab":"KOTA BEKASI","originalFilename":"0404PKS_LATU HAR HARI.jpg","namaPartai":"Partai Keadilan Sejahtera","id":191188,"noUrut":4,"nama":"LATU HAR HARY, S.Sn","stringJenisKelamin":"Laki-Laki"},{"namaKab":"KOTA BEKASI","originalFilename":"0405PKS_TRI SUPRIHATININGSIH.jpg","namaPartai":"Partai Keadilan Sejahtera","id":190966,"noUrut":5,"nama":"TRI SUPRIHATININGSIH, S.Th.I","stringJenisKelamin":"Perempuan"},{"namaKab":"KOTA BEKASI","originalFilename":"0406PKS_AHMAD MUSHODDIQ.jpg","namaPartai":"Partai Keadilan Sejahtera","id":191565,"noUrut":6,"nama":"AKHMAD MUSODIQ, S.Pd","stringJenisKelamin":"Laki-Laki"},{"namaKab":"JAKARTA SELATAN","originalFilename":"0407PKS_HJ MUTHMAINNAH SH.jpg","namaPartai":"Partai Keadilan Sejahtera","id":188467,"noUrut":7,"nama":"Hj. MUTHMAINNAH, SH","stringJenisKelamin":"Perempuan"}][{"namaKab":"KOTA BEKASI","originalFilename":"Photo Fajarin.png","namaPartai":"Persatuan Indonesia","id":22838,"noUrut":1,"nama":"FAJARIN SAHALA, SE","stringJenisKelamin":"Laki-Laki"},{"namaKab":"KOTA BEKASI","originalFilename":"9 Photo Agus.jpg","namaPartai":"Persatuan Indonesia","id":22515,"noUrut":2,"nama":"Drs. H. AGUS MULYANTO, MM","stringJenisKelamin":"Laki-Laki"},{"namaKab":"KOTA BEKASI","originalFilename":"Photo Lilis 1.png","namaPartai":"Persatuan Indonesia","id":22644,"noUrut":3,"nama":"LILIS LESTARI","stringJenisKelamin":"Perempuan"},{"namaKab":"KOTA BEKASI","originalFilename":"9. Pas Photo Irwan.jpg","namaPartai":"Persatuan Indonesia","id":53997,"noUrut":4,"nama":"IRWAN FAHRIA, SH","stringJenisKelamin":"Laki-Laki"},{"namaKab":"KOTA BEKASI","originalFilename":"boby.jpg","namaPartai":"Persatuan Indonesia","id":156935,"noUrut":5,"nama":"FERI MULPANDI","stringJenisKelamin":"Laki-Laki"},{"namaKab":"KOTA BEKASI","originalFilename":"9. Photo Sri.jpg","namaPartai":"Persatuan Indonesia","id":237229,"noUrut":6,"nama":"SRI AIRINA DEWI","stringJenisKelamin":"Perempuan"}][{"namaKab":"KOTA BEKASI","namaPartai":"Partai Persatuan pembangunan","id":237668,"noUrut":1,"nama":"H. AGUS BEJO, SE","stringJenisKelamin":"Laki-Laki"},{"namaKab":"KOTA BEKASI","namaPartai":"Partai Persatuan pembangunan","id":237815,"noUrut":2,"nama":"O.K AHMAD SYAHBANA","stringJenisKelamin":"Laki-Laki"},{"namaKab":"JAKARTA TIMUR","namaPartai":"Partai Persatuan pembangunan","id":237984,"noUrut":3,"nama":"INTAN ROSPANDAN SARI","stringJenisKelamin":"Perempuan"},{"namaKab":"KOTA PANGKALPINANG","namaPartai":"Partai Persatuan pembangunan","id":238245,"noUrut":4,"nama":"GAUNG SATRIO, S. AB","stringJenisKelamin":"Laki-Laki"},{"namaKab":"KOTA BEKASI","namaPartai":"Partai Persatuan pembangunan","id":238453,"noUrut":5,"nama":"NANANG NAJMUDIN, S. Pd","stringJenisKelamin":"Laki-Laki"},{"namaKab":"KOTA BEKASI","namaPartai":"Partai Persatuan pembangunan","id":238598,"noUrut":6,"nama":"NURLELA","stringJenisKelamin":"Perempuan"}][{"namaKab":"KOTA BEKASI","originalFilename":"ROGANDA TOGATOROP, AMD.KOM.jpg","namaPartai":"Partai Solidaritas Indonesia","id":121928,"noUrut":1,"nama":"ROGANDA TOGATOROP, AMD.KOM","stringJenisKelamin":"Perempuan"},{"namaKab":"KOTA BEKASI","originalFilename":"FLURY DWI MUSTIKA, SE.jpeg","namaPartai":"Partai Solidaritas Indonesia","id":184739,"noUrut":2,"nama":"FLURY DWI MUSTIKA, SE","stringJenisKelamin":"Perempuan"},{"namaKab":"KOTA BEKASI","originalFilename":"ANDRY JANNUS IMANUEL SIHITE.jpg","namaPartai":"Partai Solidaritas Indonesia","id":80532,"noUrut":4,"nama":"ANDRY JANNUS IMANUEL SIHITE","stringJenisKelamin":"Laki-Laki"},{"namaKab":"KOTA BEKASI","originalFilename":"SAHRUL DARSONO.jpg","namaPartai":"Partai Solidaritas Indonesia","id":160416,"noUrut":5,"nama":"SAHRUL DARSONO","stringJenisKelamin":"Laki-Laki"},{"namaKab":"KOTA BEKASI","originalFilename":"TEGUH PRIAHANTO, A.md.JPG","namaPartai":"Partai Solidaritas Indonesia","id":160716,"noUrut":6,"nama":"TEGUH PRIAHANTO, A.md","stringJenisKelamin":"Laki-Laki"},{"namaKab":"KOTA BEKASI","originalFilename":"HERMAWAN.jpeg","namaPartai":"Partai Solidaritas Indonesia","id":187393,"noUrut":7,"nama":"HERMAWAN BUDI SUSETYO, S.SI","stringJenisKelamin":"Laki-Laki"}][{"namaKab":"KOTA BEKASI","namaPartai":"PARTAI AMANAT NASIONAL","id":305561,"noUrut":1,"nama":"AHMAD SYIFA","stringJenisKelamin":"Laki-Laki"},{"namaKab":"KOTA BEKASI","originalFilename":"AHMAD JAMHIR.jpg","namaPartai":"PARTAI AMANAT NASIONAL","id":186251,"noUrut":2,"nama":"AHMAD JAMHIR HIDRON","stringJenisKelamin":"Laki-Laki"},{"namaKab":"KOTA BEKASI","namaPartai":"PARTAI AMANAT NASIONAL","id":305827,"noUrut":3,"nama":"AMINAH, S.Pd","stringJenisKelamin":"Perempuan"},{"namaKab":"KOTA BEKASI","originalFilename":"MUH. FARID PASHA SURENDRA.jpg","namaPartai":"PARTAI AMANAT NASIONAL","id":185139,"noUrut":4,"nama":"MOH. FARID PASHA SURENDRA, S.Kom. MM","stringJenisKelamin":"Laki-Laki"},{"namaKab":"BEKASI","originalFilename":"rini mardiani.jpg","namaPartai":"PARTAI AMANAT NASIONAL","id":185801,"noUrut":5,"nama":"RENI MERDIANI, SE","stringJenisKelamin":"Perempuan"},{"namaKab":"KOTA BEKASI","originalFilename":"Drs ZULKIFLI.jpg","namaPartai":"PARTAI AMANAT NASIONAL","id":187164,"noUrut":6,"nama":"Drs. ZULKIFLI","stringJenisKelamin":"Laki-Laki"},{"namaKab":"KOTA BEKASI","originalFilename":"Dr. LUTHFIA SOEGIHARTO.jpg","namaPartai":"PARTAI AMANAT NASIONAL","id":227619,"noUrut":7,"nama":"dr. LUTHFIA SOEGIHARTO","stringJenisKelamin":"Perempuan"}][{"namaKab":"KOTA DEPOK","namaPartai":"Partai Hati Nurani Rakyat","id":289177,"noUrut":1,"nama":"ARRIE YULIANTO","stringJenisKelamin":"Laki-Laki"},{"namaKab":"KOTA BEKASI","namaPartai":"Partai Hati Nurani Rakyat","id":289216,"noUrut":2,"nama":"OSHIN SARI DEWI VG","stringJenisKelamin":"Perempuan"},{"namaKab":"KOTA BEKASI","namaPartai":"Partai Hati Nurani Rakyat","id":289308,"noUrut":4,"nama":"HANAN SANAKY","stringJenisKelamin":"Laki-Laki"},{"namaKab":"KOTA BEKASI","namaPartai":"Partai Hati Nurani Rakyat","id":289321,"noUrut":5,"nama":"IRVIANTI SUDIRMAN","stringJenisKelamin":"Perempuan"},{"namaKab":"KOTA BEKASI","namaPartai":"Partai Hati Nurani Rakyat","id":289338,"noUrut":6,"nama":"NATALIA PAULINA OETOMO","stringJenisKelamin":"Perempuan"},{"namaKab":"KOTA BEKASI","namaPartai":"Partai Hati Nurani Rakyat","id":290092,"noUrut":7,"nama":"SUDI HARTONO","stringJenisKelamin":"Laki-Laki"}][{"namaKab":"KOTA BEKASI","originalFilename":"HJ ROHANIAH - FOTO.jpg","namaPartai":"PARTAI DEMOKRAT","id":189120,"noUrut":1,"nama":"HJ. ROHANIAH","stringJenisKelamin":"Perempuan"},{"namaKab":"KOTA BEKASI","originalFilename":"SUPENDI - FOTO.jpg","namaPartai":"PARTAI DEMOKRAT","id":190643,"noUrut":2,"nama":"SUPENDI","stringJenisKelamin":"Laki-Laki"},{"namaKab":"JAKARTA BARAT","originalFilename":"DWI MUHAMMAD DEWADJI - FOTO.jpg","namaPartai":"PARTAI DEMOKRAT","id":238050,"noUrut":3,"nama":"DWI MUHAMMAD DEWADJI","stringJenisKelamin":"Laki-Laki"},{"namaKab":"KOTA BEKASI","originalFilename":"SYAHRIZAL FAHMI POHAN - FOTO.JPG","namaPartai":"PARTAI DEMOKRAT","id":279500,"noUrut":4,"nama":"SYAHRIZAL FAHMI POHAN","stringJenisKelamin":"Laki-Laki"},{"namaKab":"KOTA BEKASI","originalFilename":"ERNA DAMAYANTI - PAS FOTO.jpg","namaPartai":"PARTAI DEMOKRAT","id":243746,"noUrut":5,"nama":"ERNA DAMAYANTI","stringJenisKelamin":"Perempuan"},{"namaKab":"KOTA BEKASI","originalFilename":"RICO VALENTINO - FOTO 4X6.jpg","namaPartai":"PARTAI DEMOKRAT","id":218483,"noUrut":6,"nama":"RICO VALENTINO","stringJenisKelamin":"Laki-Laki"},{"namaKab":"KOTA BEKASI","originalFilename":"LINDA LESTARI-FOTO.jpg","namaPartai":"PARTAI DEMOKRAT","id":188890,"noUrut":7,"nama":"LINDA LESTARI","stringJenisKelamin":"Perempuan"}][{"namaKab":"KOTA BEKASI","originalFilename":"DSC_8641 copy.jpg","namaPartai":"Partai Bulan Bintang","id":73891,"noUrut":1,"nama":"IKROK AZ, SE","stringJenisKelamin":"Laki-Laki"},{"namaKab":"KOTA BEKASI","originalFilename":"IMG-20180711-WA0006.jpg","namaPartai":"Partai Bulan Bintang","id":72526,"noUrut":2,"nama":"DRS. BANTA UMAR B. ALWY","stringJenisKelamin":"Laki-Laki"},{"namaKab":"KOTA BEKASI","namaPartai":"Partai Bulan Bintang","id":276424,"noUrut":4,"nama":"LILIS HANDAYANI, SE","stringJenisKelamin":"Perempuan"},{"namaKab":"KOTA BEKASI","originalFilename":"Foto Andhy Sarwo Priyono.jpg","namaPartai":"Partai Bulan Bintang","id":74654,"noUrut":5,"nama":"ANDHY SARWO PRIYONO, SE","stringJenisKelamin":"Laki-Laki"},{"namaKab":"BOGOR","originalFilename":"photo.jpg","namaPartai":"Partai Bulan Bintang","id":235431,"noUrut":6,"nama":"Dra. EKA MIRAYATUN","stringJenisKelamin":"Perempuan"}][{"namaKab":"KOTA BEKASI","originalFilename":"foto.jpeg","namaPartai":"Partai Keadilan dan Persatuan Indonesia","id":278725,"noUrut":1,"nama":"ARESIMA TABRANINTYA","stringJenisKelamin":"Perempuan"}]