[{"namaKab":"KOTA GORONTALO","originalFilename":"1. Firman.jpg","namaPartai":"Partai Hati Nurani Rakyat","id":114335,"noUrut":1,"nama":"FIRMAN FERDINAND SOENGE","stringJenisKelamin":"Laki-Laki"},{"namaKab":"PAHUWATO","originalFilename":"2. Lamuto.jpg","namaPartai":"Partai Hati Nurani Rakyat","id":282363,"noUrut":2,"nama":"LAMUTO TOWALU","stringJenisKelamin":"Laki-Laki"},{"namaKab":"PAHUWATO","originalFilename":"3. Nany.jpg","namaPartai":"Partai Hati Nurani Rakyat","id":281685,"noUrut":3,"nama":"NANY MARTHIPANY S RAZAK","stringJenisKelamin":"Perempuan"},{"namaKab":"PAHUWATO","originalFilename":"4. Raman.jpg","namaPartai":"Partai Hati Nurani Rakyat","id":281860,"noUrut":4,"nama":"RAMAN KASADI","stringJenisKelamin":"Laki-Laki"},{"namaKab":"PAHUWATO","originalFilename":"5. Wana.jpg","namaPartai":"Partai Hati Nurani Rakyat","id":281205,"noUrut":5,"nama":"WANA POLUMULO","stringJenisKelamin":"Perempuan"},{"namaKab":"BOALEMO","originalFilename":"6. Rusni.jpg","namaPartai":"Partai Hati Nurani Rakyat","id":283041,"noUrut":6,"nama":"RUSNI DAULIMA","stringJenisKelamin":"Perempuan"},{"namaKab":"PAHUWATO","originalFilename":"7. Yusran.jpg","namaPartai":"Partai Hati Nurani Rakyat","id":282150,"noUrut":7,"nama":"YUSRAN LAINDI","stringJenisKelamin":"Laki-Laki"},{"namaKab":"PAHUWATO","originalFilename":"8. Lelis.jpg","namaPartai":"Partai Hati Nurani Rakyat","id":280950,"noUrut":8,"nama":"LELIS ADAM","stringJenisKelamin":"Perempuan"},{"namaKab":"BOALEMO","originalFilename":"9. Pius.jpg","namaPartai":"Partai Hati Nurani Rakyat","id":243549,"noUrut":9,"nama":"PIUS HOROKUBUN","stringJenisKelamin":"Laki-Laki"},{"namaKab":"BOALEMO","originalFilename":"10. Sabrin.jpg","namaPartai":"Partai Hati Nurani Rakyat","id":242300,"noUrut":10,"nama":"SABRIN SAHRAIN","stringJenisKelamin":"Perempuan"},{"namaKab":"PAHUWATO","originalFilename":"2. Kasman.jpg","namaPartai":"Partai Hati Nurani Rakyat","id":277510,"noUrut":11,"nama":"KASMAN MOHAMAD","stringJenisKelamin":"Laki-Laki"}]