[{"namaKab":"SUBANG","originalFilename":"1. H. SURADEN.jpg","namaPartai":"PARTAI DEMOKRASI INDONESIA PERJUANGAN","id":77590,"noUrut":1,"nama":"H. SURADEN","stringJenisKelamin":"Laki-Laki"},{"namaKab":"SUBANG","originalFilename":"2. IMAS SUANGSIH.jpg","namaPartai":"PARTAI DEMOKRASI INDONESIA PERJUANGAN","id":77542,"noUrut":2,"nama":"IMAS SUANGSIH","stringJenisKelamin":"Perempuan"},{"namaKab":"SUBANG","originalFilename":"3. NAZIB JORDIE FATURAHMAN.jpg","namaPartai":"PARTAI DEMOKRASI INDONESIA PERJUANGAN","id":163720,"noUrut":3,"nama":"NAZIB JORDIE FATURAHMAN","stringJenisKelamin":"Laki-Laki"},{"namaKab":"SUBANG","originalFilename":"4. ABDUL RAHIM.jpg","namaPartai":"PARTAI DEMOKRASI INDONESIA PERJUANGAN","id":163901,"noUrut":4,"nama":"OING ABDUL ROHIM, S.IP","stringJenisKelamin":"Laki-Laki"},{"namaKab":"SUBANG","originalFilename":"5. SITI RODIAH.jpg","namaPartai":"PARTAI DEMOKRASI INDONESIA PERJUANGAN","id":183382,"noUrut":5,"nama":"SITI RODIAH","stringJenisKelamin":"Perempuan"},{"namaKab":"SUBANG","originalFilename":"6. DASWINTO.jpg","namaPartai":"PARTAI DEMOKRASI INDONESIA PERJUANGAN","id":77469,"noUrut":6,"nama":"DASWINTO","stringJenisKelamin":"Laki-Laki"}]