[{"namaKab":"SAMBAS","originalFilename":"8_1.jpg","namaPartai":"Partai Keadilan Sejahtera","id":102700,"noUrut":1,"nama":"ARPANDI, SP","stringJenisKelamin":"Laki-Laki"},{"namaKab":"SAMBAS","originalFilename":"8_2.jpg","namaPartai":"Partai Keadilan Sejahtera","id":102479,"noUrut":2,"nama":"HJ. ASIAH","stringJenisKelamin":"Perempuan"},{"namaKab":"SAMBAS","originalFilename":"8_3.jpg","namaPartai":"Partai Keadilan Sejahtera","id":153788,"noUrut":3,"nama":"KARMADI","stringJenisKelamin":"Laki-Laki"},{"namaKab":"SAMBAS","originalFilename":"8_4.jpg","namaPartai":"Partai Keadilan Sejahtera","id":145750,"noUrut":4,"nama":"SYAHRUDIN, ST","stringJenisKelamin":"Laki-Laki"},{"namaKab":"SAMBAS","originalFilename":"8_5.jpg","namaPartai":"Partai Keadilan Sejahtera","id":145984,"noUrut":5,"nama":"DALILA, S.Pd","stringJenisKelamin":"Perempuan"},{"namaKab":"SAMBAS","originalFilename":"8_6.jpg","namaPartai":"Partai Keadilan Sejahtera","id":160839,"noUrut":6,"nama":"ARIANDI","stringJenisKelamin":"Laki-Laki"},{"namaKab":"SAMBAS","originalFilename":"8_7.jpg","namaPartai":"Partai Keadilan Sejahtera","id":159303,"noUrut":7,"nama":"ARIFIN USMAN","stringJenisKelamin":"Laki-Laki"},{"namaKab":"SAMBAS","originalFilename":"8_8.jpg","namaPartai":"Partai Keadilan Sejahtera","id":146547,"noUrut":8,"nama":"SUFIAN","stringJenisKelamin":"Laki-Laki"},{"namaKab":"SAMBAS","originalFilename":"8_9.jpg","namaPartai":"Partai Keadilan Sejahtera","id":145620,"noUrut":9,"nama":"LILIS SUHERTI","stringJenisKelamin":"Perempuan"},{"namaKab":"SAMBAS","originalFilename":"8_10.jpg","namaPartai":"Partai Keadilan Sejahtera","id":161417,"noUrut":10,"nama":"DARE","stringJenisKelamin":"Perempuan"},{"namaKab":"SAMBAS","originalFilename":"8_11.jpg","namaPartai":"Partai Keadilan Sejahtera","id":152420,"noUrut":11,"nama":"NAZARUDIN, SP","stringJenisKelamin":"Laki-Laki"}]