[{"namaKab":"SUMENEP","originalFilename":"FOTO PAK joni.jpg","namaPartai":"PARTAI DEMOKRAT","id":120910,"noUrut":1,"nama":"R.ACH.DJONI TUNAIDY, S.Sos","stringJenisKelamin":"Laki-Laki"},{"namaKab":"SUMENEP","originalFilename":"DRS HASANUDIN.jpg","namaPartai":"PARTAI DEMOKRAT","id":56130,"noUrut":2,"nama":"Drs. MOH.HASANUDIN, SH","stringJenisKelamin":"Laki-Laki"},{"namaKab":"SUMENEP","originalFilename":"FOTO LATIFA.jpg","namaPartai":"PARTAI DEMOKRAT","id":231224,"noUrut":3,"nama":"LATIFA","stringJenisKelamin":"Perempuan"},{"namaKab":"SUMENEP","originalFilename":"FOTO ALDIANSYA.jpg","namaPartai":"PARTAI DEMOKRAT","id":121134,"noUrut":4,"nama":"RYAN ALDIANSYAH AKBAR, ST","stringJenisKelamin":"Laki-Laki"},{"namaKab":"SUMENEP","originalFilename":"DIDIK UNTUNG OK.jpg","namaPartai":"PARTAI DEMOKRAT","id":245460,"noUrut":5,"nama":"Drs.Ec. DIDIK UNTUNG SAMSIDI, MM","stringJenisKelamin":"Laki-Laki"},{"namaKab":"SUMENEP","originalFilename":"FOTO alia.jpg","namaPartai":"PARTAI DEMOKRAT","id":73396,"noUrut":6,"nama":"ALIA NUR AFDHALINA, ST","stringJenisKelamin":"Perempuan"},{"namaKab":"SUMENEP","originalFilename":"IMG_4605.jpg","namaPartai":"PARTAI DEMOKRAT","id":73567,"noUrut":7,"nama":"Ir. H. YUSUF ISMAIL","stringJenisKelamin":"Laki-Laki"},{"namaKab":"SUMENEP","originalFilename":"4x6.jpg","namaPartai":"PARTAI DEMOKRAT","id":56183,"noUrut":8,"nama":"WINANTO, SE","stringJenisKelamin":"Laki-Laki"},{"namaKab":"SUMENEP","originalFilename":"FOTO NUR AINI.jpg","namaPartai":"PARTAI DEMOKRAT","id":74078,"noUrut":9,"nama":"NUR AINI","stringJenisKelamin":"Perempuan"}]