[{"namaKab":"TIMOR TENGAH SELATAN","originalFilename":"JULIANA MAKANDOLU.jpg","namaPartai":"PARTAI GERAKAN INDONESIA RAYA","id":5891,"noUrut":1,"nama":"JULIANA DESDEMONA MAKANDOLU","stringJenisKelamin":"Perempuan"},{"namaKab":"TIMOR TENGAH SELATAN","originalFilename":"HABEL A. HOTTY.jpg","namaPartai":"PARTAI GERAKAN INDONESIA RAYA","id":46159,"noUrut":2,"nama":"HABEL APELES HOTTY","stringJenisKelamin":"Laki-Laki"},{"namaKab":"TIMOR TENGAH SELATAN","originalFilename":"FRANS NENOBAIS.jpg","namaPartai":"PARTAI GERAKAN INDONESIA RAYA","id":55210,"noUrut":3,"nama":"FRANAS NENOBAIS","stringJenisKelamin":"Laki-Laki"},{"namaKab":"TIMOR TENGAH SELATAN","originalFilename":"BEN O. TALAN.jpg","namaPartai":"PARTAI GERAKAN INDONESIA RAYA","id":55324,"noUrut":4,"nama":"BEN ONISIUS TALAN","stringJenisKelamin":"Laki-Laki"},{"namaKab":"TIMOR TENGAH SELATAN","originalFilename":"ADRIANA ROHI.jpg","namaPartai":"PARTAI GERAKAN INDONESIA RAYA","id":45585,"noUrut":5,"nama":"ADRIANA ROHI","stringJenisKelamin":"Perempuan"},{"namaKab":"TIMOR TENGAH SELATAN","originalFilename":"CHARLES TOBE.jpg","namaPartai":"PARTAI GERAKAN INDONESIA RAYA","id":55290,"noUrut":6,"nama":"CHARLES ABRAHAM TOBE, SH","stringJenisKelamin":"Laki-Laki"},{"namaKab":"TIMOR TENGAH SELATAN","originalFilename":"DEMARIS SELAN.jpg","namaPartai":"PARTAI GERAKAN INDONESIA RAYA","id":43304,"noUrut":7,"nama":"DEMARIS JUBLINA SELAN","stringJenisKelamin":"Perempuan"},{"namaKab":"TIMOR TENGAH SELATAN","originalFilename":"OKTOVIANUS SELAN.jpg","namaPartai":"PARTAI GERAKAN INDONESIA RAYA","id":6336,"noUrut":8,"nama":"OKTOVIANUS SELAN, A.Md","stringJenisKelamin":"Laki-Laki"}]