[{"namaKab":"TANGERANG","originalFilename":"10. FOTO.jpg","namaPartai":"Partai Bulan Bintang","id":25310,"noUrut":1,"nama":"ALI JAYA MULYA","stringJenisKelamin":"Laki-Laki"},{"namaKab":"TANGERANG","originalFilename":"2.JPG","namaPartai":"Partai Bulan Bintang","id":17150,"noUrut":2,"nama":"JAENUL MURSOPI","stringJenisKelamin":"Laki-Laki"},{"namaKab":"TANGERANG","originalFilename":"10. FOTO.jpeg","namaPartai":"Partai Bulan Bintang","id":130242,"noUrut":3,"nama":"ILAH ROHILAH","stringJenisKelamin":"Perempuan"},{"namaKab":"TANGERANG","originalFilename":"10. FOTO.jpg","namaPartai":"Partai Bulan Bintang","id":17013,"noUrut":4,"nama":"HASIM ADNAN","stringJenisKelamin":"Laki-Laki"},{"namaKab":"TANGERANG","originalFilename":"10. FOTO.jpg","namaPartai":"Partai Bulan Bintang","id":261934,"noUrut":5,"nama":"LENNY WILDA HARDIANTI","stringJenisKelamin":"Perempuan"},{"namaKab":"TANGERANG","originalFilename":"R.jpg","namaPartai":"Partai Bulan Bintang","id":1519,"noUrut":6,"nama":"AHMAD HIZBULLAH","stringJenisKelamin":"Laki-Laki"},{"namaKab":"TANGERANG","originalFilename":"10. FOTO.jpg","namaPartai":"Partai Bulan Bintang","id":262015,"noUrut":7,"nama":"MEI UTAMI","stringJenisKelamin":"Perempuan"}]