[{"namaKab":"KOTA BANDUNG","originalFilename":"WhatsApp Image 2018-07-18 at 05.32.50.jpeg","namaPartai":"Partai Gerakan Perubahan Indonesia","id":245350,"noUrut":1,"nama":"MUHAMAD REZA IMAMMI","stringJenisKelamin":"Laki-Laki"},{"namaKab":"BANDUNG","originalFilename":"IMG-20180727-WA0046.jpg","namaPartai":"Partai Gerakan Perubahan Indonesia","id":253049,"noUrut":2,"nama":"ECKA TUTI WIDIASTUTI","stringJenisKelamin":"Perempuan"},{"namaKab":"KOTA BANDUNG","originalFilename":"46 CL.jpg","namaPartai":"Partai Gerakan Perubahan Indonesia","id":254396,"noUrut":3,"nama":"DEVY WIDYA APRIANDI, SE., MBA","stringJenisKelamin":"Laki-Laki"},{"namaKab":"KOTA BANDUNG","originalFilename":"IMG-20180919-WA0019.jpg","namaPartai":"Partai Gerakan Perubahan Indonesia","id":255088,"noUrut":4,"nama":"NIA WARNIA","stringJenisKelamin":"Perempuan"},{"namaKab":"KOTA BANDUNG","originalFilename":"WhatsApp Image 2018-07-18 at 05.25.38.jpeg","namaPartai":"Partai Gerakan Perubahan Indonesia","id":255731,"noUrut":5,"nama":"NANANG BURHAN","stringJenisKelamin":"Laki-Laki"},{"namaKab":"KOTA BANDUNG","originalFilename":"46.jpg","namaPartai":"Partai Gerakan Perubahan Indonesia","id":275798,"noUrut":6,"nama":"IR. TRINADI RUDI HERYADI","stringJenisKelamin":"Laki-Laki"}]