[{"namaKab":"JAKARTA PUSAT","originalFilename":"Dr. Amir Syamsudin, SH, MH.jpg","namaPartai":"PARTAI DEMOKRAT","id":147579,"noUrut":1,"nama":"Dr. AMIR SYAMSUDIN, SH.,MH.","stringJenisKelamin":"Laki-Laki"},{"namaKab":"KOTA SERANG","originalFilename":"foto Nur Aeni-croped.jpg","namaPartai":"PARTAI DEMOKRAT","id":258419,"noUrut":2,"nama":"NUR AENI","stringJenisKelamin":"Perempuan"},{"namaKab":"KOTA SERANG","originalFilename":"FOTO A\u0027ENK.jpg","namaPartai":"PARTAI DEMOKRAT","id":148519,"noUrut":3,"nama":"H. AENG HAERUDIN","stringJenisKelamin":"Laki-Laki"},{"namaKab":"KOTA SERANG","originalFilename":"04-H. AYIP NAJIB (DUCE)-reformat.jpg","namaPartai":"PARTAI DEMOKRAT","id":146184,"noUrut":4,"nama":"H. AYIP NAJIB (DUCE)","stringJenisKelamin":"Laki-Laki"},{"namaKab":"KOTA DEPOK","originalFilename":"05-H.AHMAD RIFAI SUFTYADI, SH.JPG","namaPartai":"PARTAI DEMOKRAT","id":150677,"noUrut":5,"nama":"H.AHMAD RIFAI SUFTYADI, SH","stringJenisKelamin":"Laki-Laki"},{"namaKab":"JAKARTA BARAT","originalFilename":"FOTO LINDA AGUSTIN A.jpg","namaPartai":"PARTAI DEMOKRAT","id":147145,"noUrut":6,"nama":"LINDA AGUSTINI ARITONANG, SS","stringJenisKelamin":"Perempuan"}]