[{"namaKab":"MIMIKA","originalFilename":"img442.jpg","namaPartai":"PARTAI GERAKAN INDONESIA RAYA","id":258655,"noUrut":1,"nama":"MARCIANUS TAWURUTUBUN, SE","stringJenisKelamin":"Laki-Laki"},{"namaKab":"MIMIKA","originalFilename":"img034.jpg","namaPartai":"PARTAI GERAKAN INDONESIA RAYA","id":209460,"noUrut":2,"nama":"YULI UNGSIADI, A.Md.Kep","stringJenisKelamin":"Laki-Laki"},{"namaKab":"MIMIKA","originalFilename":"img787.jpg","namaPartai":"PARTAI GERAKAN INDONESIA RAYA","id":270800,"noUrut":3,"nama":"YOWENA MURIB","stringJenisKelamin":"Perempuan"},{"namaKab":"MIMIKA","originalFilename":"img429.jpg","namaPartai":"PARTAI GERAKAN INDONESIA RAYA","id":258257,"noUrut":4,"nama":"YOEL MAGAI, ST","stringJenisKelamin":"Laki-Laki"},{"namaKab":"MIMIKA","originalFilename":"img304.jpg","namaPartai":"PARTAI GERAKAN INDONESIA RAYA","id":222331,"noUrut":5,"nama":"FRANS ALBERTH KOPEUW","stringJenisKelamin":"Laki-Laki"},{"namaKab":"MIMIKA","originalFilename":"jesica tambalean.jpg","namaPartai":"PARTAI GERAKAN INDONESIA RAYA","id":258916,"noUrut":6,"nama":"JESSICA TAMBALEAN","stringJenisKelamin":"Perempuan"}]