[{"namaKab":"KOTA SINGKAWANG","originalFilename":"4x6.jpg","namaPartai":"PARTAI DEMOKRAT","id":223645,"noUrut":1,"nama":"Drs. TAVIP PUTRA PURBA","stringJenisKelamin":"Laki-Laki"},{"namaKab":"KOTA SINGKAWANG","originalFilename":"4x6.jpg","namaPartai":"PARTAI DEMOKRAT","id":223806,"noUrut":2,"nama":"MUKSIN","stringJenisKelamin":"Laki-Laki"},{"namaKab":"KOTA SINGKAWANG","originalFilename":"4x6.jpg","namaPartai":"PARTAI DEMOKRAT","id":223968,"noUrut":3,"nama":"NERRY VIDIANY  SITOHANG, S.H","stringJenisKelamin":"Perempuan"},{"namaKab":"KOTA SINGKAWANG","originalFilename":"4x6.jpg","namaPartai":"PARTAI DEMOKRAT","id":230514,"noUrut":4,"nama":"ZULKARNAIN, S.Sos","stringJenisKelamin":"Laki-Laki"},{"namaKab":"KOTA SINGKAWANG","originalFilename":"4x6.jpg","namaPartai":"PARTAI DEMOKRAT","id":206703,"noUrut":5,"nama":"NELLY APRIYANTI, S.Ds","stringJenisKelamin":"Perempuan"},{"namaKab":"KOTA SINGKAWANG","originalFilename":"4x6.jpg","namaPartai":"PARTAI DEMOKRAT","id":230058,"noUrut":6,"nama":"EDHY PRAJITNO","stringJenisKelamin":"Laki-Laki"},{"namaKab":"KOTA SINGKAWANG","originalFilename":"4x6.jpg","namaPartai":"PARTAI DEMOKRAT","id":229438,"noUrut":7,"nama":"RENITA WULANDARI, S.Pd","stringJenisKelamin":"Perempuan"},{"namaKab":"KOTA SINGKAWANG","originalFilename":"4x6.jpg","namaPartai":"PARTAI DEMOKRAT","id":230856,"noUrut":8,"nama":"DWI ANGGA SAPUTRA","stringJenisKelamin":"Laki-Laki"}]