[{"namaKab":"MOJOKERTO","originalFilename":"1. LUTFI CHAKIM.jpg","namaPartai":"PARTAI DEMOKRAT","id":254330,"noUrut":1,"nama":"LUTFI KHAKIM","stringJenisKelamin":"Laki-Laki"},{"namaKab":"MOJOKERTO","originalFilename":"2.  H. MOKHMMAD SOLEH, S.Sos.jpg","namaPartai":"PARTAI DEMOKRAT","id":71800,"noUrut":2,"nama":"H. MOKHAMMAD SOLEH, S.Sos.","stringJenisKelamin":"Laki-Laki"},{"namaKab":"MOJOKERTO","originalFilename":"3. RINA FARDIATI.jpg","namaPartai":"PARTAI DEMOKRAT","id":71785,"noUrut":3,"nama":"RINA FARDIATI","stringJenisKelamin":"Perempuan"},{"namaKab":"MOJOKERTO","originalFilename":"4. BUDI PRIHATINI.jpg","namaPartai":"PARTAI DEMOKRAT","id":137309,"noUrut":4,"nama":"BUDI PRIHATINI","stringJenisKelamin":"Perempuan"},{"namaKab":"MOJOKERTO","originalFilename":"5. TEGUH INDAR PERMANA, S.Pd.jpg","namaPartai":"PARTAI DEMOKRAT","id":62633,"noUrut":5,"nama":"TEGUH INDAR PERMANA, S.Pd.","stringJenisKelamin":"Laki-Laki"},{"namaKab":"MOJOKERTO","originalFilename":"6. YUNITA VERONICA.jpg","namaPartai":"PARTAI DEMOKRAT","id":135393,"noUrut":6,"nama":"YUNITA VERONICA","stringJenisKelamin":"Perempuan"},{"namaKab":"MOJOKERTO","originalFilename":"7. ANI SAIDAH.jpeg","namaPartai":"PARTAI DEMOKRAT","id":105876,"noUrut":7,"nama":"ANI SAIDAH","stringJenisKelamin":"Perempuan"},{"namaKab":"MOJOKERTO","originalFilename":"8. IFA SUSANTI.jpeg","namaPartai":"PARTAI DEMOKRAT","id":105531,"noUrut":8,"nama":"IFA SUSANTI","stringJenisKelamin":"Perempuan"}]