[{"namaKab":"KOTA KENDARI","originalFilename":"FOTO BARU.jpg","namaPartai":"PARTAI GERAKAN INDONESIA RAYA","id":2280,"noUrut":1,"nama":"HASRIL, ST","stringJenisKelamin":"Laki-Laki"},{"namaKab":"KOTA KENDARI","originalFilename":"DSC_8914.JPG","namaPartai":"Partai Bulan Bintang","id":2502,"noUrut":1,"nama":"HAMILI, S.Pd.","stringJenisKelamin":"Laki-Laki"},{"namaKab":"KOTA KENDARI","originalFilename":"FOTO.jpg","namaPartai":"PARTAI AMANAT NASIONAL","id":14124,"noUrut":1,"nama":"BAHAR, S.Sos.","stringJenisKelamin":"Laki-Laki"},{"namaKab":"KOTA KENDARI","originalFilename":"NURDIN POASIA.jpg","namaPartai":"PARTAI DEMOKRAT","id":41377,"noUrut":1,"nama":"NURDIN, S.Pd.","stringJenisKelamin":"Laki-Laki"},{"namaKab":"KOTA KENDARI","originalFilename":"LA YULI.JPG","namaPartai":"Partai Keadilan Sejahtera","id":53813,"noUrut":1,"nama":"LA YULI, S.Pd.,M.Pd.","stringJenisKelamin":"Laki-Laki"},{"namaKab":"KOTA KENDARI","originalFilename":"AGUSTINA.JPG","namaPartai":"Persatuan Indonesia","id":61730,"noUrut":1,"nama":"AGUSTINA","stringJenisKelamin":"Perempuan"},{"namaKab":"KOTA KENDARI","originalFilename":"01 RUSIAWATI ABUNAWAS,SE.jpg","namaPartai":"Partai Golongan Karya","id":73808,"noUrut":1,"nama":"RUSIAHWATI ABUNAWAS, S.E.","stringJenisKelamin":"Perempuan"},{"namaKab":"KOTA KENDARI","originalFilename":"ILHAM.jpg","namaPartai":"Partai Hati Nurani Rakyat","id":111763,"noUrut":1,"nama":"Drs.. ILHAM AHMAD, -","stringJenisKelamin":"Laki-Laki"},{"namaKab":"KOTA KENDARI","originalFilename":"LA ODE LAWAMA.jpeg","namaPartai":"PARTAI DEMOKRASI INDONESIA PERJUANGAN","id":145108,"noUrut":1,"nama":"LA ODE LAWAMA, S.H.","stringJenisKelamin":"Laki-Laki"},{"namaKab":"KOTA KENDARI","originalFilename":"3.1 Hj Farida saranani.jpg","namaPartai":"Partai Persatuan pembangunan","id":154272,"noUrut":1,"nama":"HJ. FARIDA SARANANI, S.H.","stringJenisKelamin":"Perempuan"},{"namaKab":"KOTA KENDARI","originalFilename":"abdul rasak.jpg","namaPartai":"Partai NasDem","id":176721,"noUrut":1,"nama":"ABDUL RASAK, S.P.","stringJenisKelamin":"Laki-Laki"},{"namaKab":"KOTA KENDARI","originalFilename":"IMG_0651 edit.jpg","namaPartai":"Partai Kebangkitan Bangsa","id":209975,"noUrut":1,"nama":"DANIL SAHRIR","stringJenisKelamin":"Laki-Laki"},{"namaKab":"KOTA KENDARI","originalFilename":"Foto Marlian.jpg","namaPartai":"Partai Gerakan Perubahan Indonesia","id":213770,"noUrut":1,"nama":"MARLIAN ANI SAPUTRI, S.E.","stringJenisKelamin":"Perempuan"},{"namaKab":"KOTA KENDARI","originalFilename":"FOTO.jpg","namaPartai":"Partai Solidaritas Indonesia","id":255715,"noUrut":1,"nama":"MUHAMMAD ASWAD RIVALDY","stringJenisKelamin":"Laki-Laki"},{"namaKab":"KOTA KENDARI","originalFilename":"Aldhynesa Ardhana Said.JPG","namaPartai":"Partai Bulan Bintang","id":2477,"noUrut":2,"nama":"ALDHYNESA ARDHANA SAID","stringJenisKelamin":"Laki-Laki"},{"namaKab":"KOTA KENDARI","originalFilename":"FOTO ABD. MUSTAND PASAENO.jpg","namaPartai":"Persatuan Indonesia","id":28571,"noUrut":2,"nama":"ABD. MUSTAND PASAENO, S.H., M.H.","stringJenisKelamin":"Laki-Laki"},{"namaKab":"KOTA KENDARI","originalFilename":"PAS FOTO 4X6.jpg","namaPartai":"PARTAI GERAKAN INDONESIA RAYA","id":34106,"noUrut":2,"nama":"HAJI ALIAS, S.AG","stringJenisKelamin":"Laki-Laki"},{"namaKab":"KOTA KENDARI","originalFilename":"SAUDIN.jpg","namaPartai":"Partai Hati Nurani Rakyat","id":42826,"noUrut":2,"nama":"SAUDIN","stringJenisKelamin":"Laki-Laki"},{"namaKab":"KOTA KENDARI","originalFilename":"ILHAM.jpg","namaPartai":"PARTAI DEMOKRAT","id":43345,"noUrut":2,"nama":"Ir. ILHAM HAMRAH","stringJenisKelamin":"Laki-Laki"},{"namaKab":"KOTA KENDARI","originalFilename":"A.jpg","namaPartai":"Partai Kebangkitan Bangsa","id":44944,"noUrut":2,"nama":"Drs. BASRAN TADJUDIN","stringJenisKelamin":"Laki-Laki"},{"namaKab":"KOTA KENDARI","originalFilename":"CDD.jpg","namaPartai":"Partai Keadilan Sejahtera","id":48768,"noUrut":2,"nama":"SYARIFUDDIN, S.Pd","stringJenisKelamin":"Laki-Laki"},{"namaKab":"KOTA KENDARI","originalFilename":"02 JUMRAN,SE.jpg","namaPartai":"Partai Golongan Karya","id":74916,"noUrut":2,"nama":"JUMRAN, SE","stringJenisKelamin":"Laki-Laki"},{"namaKab":"KOTA KENDARI","originalFilename":"MARYATI.jpeg","namaPartai":"PARTAI DEMOKRASI INDONESIA PERJUANGAN","id":83983,"noUrut":2,"nama":"MARYATI, S.H","stringJenisKelamin":"Perempuan"},{"namaKab":"KOTA KENDARI","originalFilename":"FOTO.jpg","namaPartai":"PARTAI AMANAT NASIONAL","id":126491,"noUrut":2,"nama":"IRWAN SUKMA","stringJenisKelamin":"Laki-Laki"},{"namaKab":"KOTA KENDARI","originalFilename":"3.2 mansur.jpg","namaPartai":"Partai Persatuan pembangunan","id":157696,"noUrut":2,"nama":"NURHAYATI","stringJenisKelamin":"Perempuan"},{"namaKab":"KOTA KENDARI","originalFilename":"reski handayani.jpg","namaPartai":"Partai NasDem","id":177337,"noUrut":2,"nama":"RIZKI HANDAYANI, A.Md.Kep","stringJenisKelamin":"Perempuan"},{"namaKab":"KOTA KENDARI","originalFilename":"Foto Chaidir.jpg","namaPartai":"Partai Gerakan Perubahan Indonesia","id":215270,"noUrut":2,"nama":"MUHAMMAD CHAIDIR SYAM KADIR","stringJenisKelamin":"Laki-Laki"},{"namaKab":"KOTA KENDARI","originalFilename":"foto.jpg","namaPartai":"Partai Solidaritas Indonesia","id":256551,"noUrut":2,"nama":"ARLIN, S.H.","stringJenisKelamin":"Laki-Laki"},{"namaKab":"KOTA KENDARI","originalFilename":"4x6.jpg","namaPartai":"Partai Bulan Bintang","id":2511,"noUrut":3,"nama":"HASMIRA INDAH, S.Ars","stringJenisKelamin":"Perempuan"},{"namaKab":"KOTA KENDARI","originalFilename":"DSC_7667.JPG","namaPartai":"PARTAI GERAKAN INDONESIA RAYA","id":24417,"noUrut":3,"nama":"MEGA UTAMI RAKHMAT","stringJenisKelamin":"Perempuan"},{"namaKab":"KOTA KENDARI","originalFilename":"FOTO.jpg","namaPartai":"PARTAI AMANAT NASIONAL","id":25472,"noUrut":3,"nama":"SURIANI","stringJenisKelamin":"Perempuan"},{"namaKab":"KOTA KENDARI","originalFilename":"NURALAM.jpg","namaPartai":"PARTAI DEMOKRAT","id":45280,"noUrut":3,"nama":"NUR ALAM USMAN, SE","stringJenisKelamin":"Perempuan"},{"namaKab":"KOTA KENDARI","originalFilename":"SYUKUR SPD.jpg","namaPartai":"PARTAI DEMOKRASI INDONESIA PERJUANGAN","id":62607,"noUrut":3,"nama":"SYUKUR, S.Pd","stringJenisKelamin":"Laki-Laki"},{"namaKab":"KOTA KENDARI","originalFilename":"FOTO.jpg","namaPartai":"Partai Keadilan Sejahtera","id":63732,"noUrut":3,"nama":"HASNI","stringJenisKelamin":"Perempuan"},{"namaKab":"KOTA BANDUNG","originalFilename":"03 NOVAR ADITYA PRAJA.jpg","namaPartai":"Partai Golongan Karya","id":82496,"noUrut":3,"nama":"NOVAR ADITYA PRAJA","stringJenisKelamin":"Laki-Laki"},{"namaKab":"KOTA KENDARI","originalFilename":"Foto Sri Suwarni.jpg","namaPartai":"Partai Kebangkitan Bangsa","id":101250,"noUrut":3,"nama":"SRI SUWARNI RUSMAN","stringJenisKelamin":"Perempuan"},{"namaKab":"KOTA KENDARI","originalFilename":"NOVITA1.jpg","namaPartai":"Partai Hati Nurani Rakyat","id":114713,"noUrut":3,"nama":"-. NOVITA, S.Sos","stringJenisKelamin":"Perempuan"},{"namaKab":"KOTA KENDARI","originalFilename":"Anwar.jpg","namaPartai":"Partai NasDem","id":167259,"noUrut":3,"nama":"ANWAR","stringJenisKelamin":"Laki-Laki"},{"namaKab":"KOTA KENDARI","originalFilename":"LENNI IRAWATY.JPG","namaPartai":"Persatuan Indonesia","id":189991,"noUrut":3,"nama":"LENI IRAWATI","stringJenisKelamin":"Perempuan"},{"namaKab":"KOTA KENDARI","originalFilename":"foto.jpg","namaPartai":"Partai Solidaritas Indonesia","id":224032,"noUrut":3,"nama":"REZKI MUSDALIFA, S.H","stringJenisKelamin":"Perempuan"},{"namaKab":"KOTA KENDARI","originalFilename":"3.3 Sarif Albanda.jpg","namaPartai":"Partai Persatuan pembangunan","id":242274,"noUrut":3,"nama":"SARIF ALBANDA, SKM","stringJenisKelamin":"Laki-Laki"},{"namaKab":"KOTA KENDARI","originalFilename":"CDM_6947.JPG","namaPartai":"Partai Bulan Bintang","id":2486,"noUrut":4,"nama":"ANDI SYAFIUDDIN","stringJenisKelamin":"Laki-Laki"},{"namaKab":"KOTA KENDARI","originalFilename":"FOTO OK.jpg","namaPartai":"PARTAI GERAKAN INDONESIA RAYA","id":34161,"noUrut":4,"nama":"SUNIWAN, S.Sos","stringJenisKelamin":"Perempuan"},{"namaKab":"KOTA KENDARI","originalFilename":"ZULFIKAR.jpg","namaPartai":"PARTAI DEMOKRAT","id":43966,"noUrut":4,"nama":"ZULFIKAR ALI BUTHO","stringJenisKelamin":"Laki-Laki"},{"namaKab":"KOTA KENDARI","originalFilename":"FOTO.JPG","namaPartai":"Partai Keadilan Sejahtera","id":61883,"noUrut":4,"nama":"SAPARUDDIN","stringJenisKelamin":"Laki-Laki"},{"namaKab":"KOTA KENDARI","originalFilename":"EDISON.jpeg","namaPartai":"PARTAI DEMOKRASI INDONESIA PERJUANGAN","id":62823,"noUrut":4,"nama":"EDISON, SE","stringJenisKelamin":"Laki-Laki"},{"namaKab":"KOTA KENDARI","originalFilename":"04 MUH.RAHMAN,A,MD.jpg","namaPartai":"Partai Golongan Karya","id":75104,"noUrut":4,"nama":"MUHAMMAD RAHMAN, A.Md","stringJenisKelamin":"Laki-Laki"},{"namaKab":"KOTA KENDARI","originalFilename":"FOTO.jpg","namaPartai":"PARTAI AMANAT NASIONAL","id":122383,"noUrut":4,"nama":"ANDINI SUCIANI NAKITARA","stringJenisKelamin":"Perempuan"},{"namaKab":"KOTA KENDARI","originalFilename":"3.4 La Ode Husen.JPG","namaPartai":"Partai Persatuan pembangunan","id":151167,"noUrut":4,"nama":"LA ODE HUSEN","stringJenisKelamin":"Laki-Laki"},{"namaKab":"KOTA KENDARI","originalFilename":"mutmainna.jpg","namaPartai":"Partai NasDem","id":165248,"noUrut":4,"nama":"MUTMAINNA, S.IP","stringJenisKelamin":"Perempuan"},{"namaKab":"KOTA KENDARI","originalFilename":"Foto Rahmatia.JPG","namaPartai":"Partai Kebangkitan Bangsa","id":173389,"noUrut":4,"nama":"RAHMATIA","stringJenisKelamin":"Perempuan"},{"namaKab":"KOTA KENDARI","originalFilename":"SITTI ALANG.JPG","namaPartai":"Persatuan Indonesia","id":190181,"noUrut":4,"nama":"SITTI ALANG","stringJenisKelamin":"Perempuan"},{"namaKab":"KOTA KENDARI","originalFilename":"SYAMSUDDIN1.jpg","namaPartai":"Partai Hati Nurani Rakyat","id":209434,"noUrut":4,"nama":"-. SYAMSUDDIN, SH","stringJenisKelamin":"Laki-Laki"},{"namaKab":"KOTA KENDARI","originalFilename":"WhatsApp Image 2018-07-08 at 13.44.00.jpeg","namaPartai":"Partai Bulan Bintang","id":2495,"noUrut":5,"nama":"MUHAMMAD ALI AKBAR, SH","stringJenisKelamin":"Laki-Laki"},{"namaKab":"KOTA KENDARI","originalFilename":"FOTO OK.JPG","namaPartai":"PARTAI GERAKAN INDONESIA RAYA","id":24696,"noUrut":5,"nama":"NAZARUDIN","stringJenisKelamin":"Laki-Laki"},{"namaKab":"KOTA KENDARI","originalFilename":"FIRNA.jpg","namaPartai":"PARTAI DEMOKRAT","id":45858,"noUrut":5,"nama":"FIRNA DWI RISMARIANTI, SE","stringJenisKelamin":"Perempuan"},{"namaKab":"KOTA KENDARI","originalFilename":"05 WA ODE NURLIANA,SPd.jpg","namaPartai":"Partai Golongan Karya","id":74146,"noUrut":5,"nama":"WA ODE NURLIANA, S.PD","stringJenisKelamin":"Perempuan"},{"namaKab":"KOTA KENDARI","originalFilename":"ABD_2033.JPG","namaPartai":"Partai Keadilan Sejahtera","id":87462,"noUrut":5,"nama":"NAIMA","stringJenisKelamin":"Perempuan"},{"namaKab":"KONAWE SELATAN","originalFilename":"FOTO.jpg","namaPartai":"PARTAI AMANAT NASIONAL","id":105443,"noUrut":5,"nama":"JUSWAN, S.Sos","stringJenisKelamin":"Laki-Laki"},{"namaKab":"JAKARTA TIMUR","originalFilename":"3.5 Yusrin.jpg","namaPartai":"Partai Persatuan pembangunan","id":144634,"noUrut":5,"nama":"MUH. YUSRIN YOSEN","stringJenisKelamin":"Laki-Laki"},{"namaKab":"KOTA KENDARI","originalFilename":"rahmat suam.jpg","namaPartai":"Partai NasDem","id":175664,"noUrut":5,"nama":"RAHMAT SUAM","stringJenisKelamin":"Laki-Laki"},{"namaKab":"KOTA KENDARI","originalFilename":"MEI S L1.jpg","namaPartai":"Partai Hati Nurani Rakyat","id":183702,"noUrut":5,"nama":"-. MEI SRI LESTARI, -","stringJenisKelamin":"Perempuan"},{"namaKab":"KOTA KENDARI","originalFilename":"FOTO BURHAN.jpg","namaPartai":"Persatuan Indonesia","id":190292,"noUrut":5,"nama":"BURHAN","stringJenisKelamin":"Laki-Laki"},{"namaKab":"KOTA KENDARI","originalFilename":"cd (3)dd.jpg","namaPartai":"Partai Kebangkitan Bangsa","id":236761,"noUrut":5,"nama":"ALIMIN","stringJenisKelamin":"Laki-Laki"},{"namaKab":"KOTA KENDARI","originalFilename":"SANTI 001.jpg","namaPartai":"PARTAI DEMOKRASI INDONESIA PERJUANGAN","id":293212,"noUrut":5,"nama":"HUSRIYANTI","stringJenisKelamin":"Perempuan"},{"namaKab":"KOTA KENDARI","originalFilename":"Rustin, S.Si.jpg","namaPartai":"Partai Bulan Bintang","id":2520,"noUrut":6,"nama":"RUSTIN, S.Si","stringJenisKelamin":"Perempuan"},{"namaKab":"KOTA KENDARI","originalFilename":"FOTO.jpg","namaPartai":"PARTAI AMANAT NASIONAL","id":25775,"noUrut":6,"nama":"SYAHYUDDIN, S.Sos","stringJenisKelamin":"Laki-Laki"},{"namaKab":"KOTA KENDARI","originalFilename":"ZURISMAN.jpg","namaPartai":"PARTAI DEMOKRAT","id":40621,"noUrut":6,"nama":"ZURISMAN ZAKARIA, S.Sos.,M.Pd.","stringJenisKelamin":"Laki-Laki"},{"namaKab":"KOTA KENDARI","originalFilename":"DSC_0779 c1.jpg","namaPartai":"Partai Keadilan Sejahtera","id":53987,"noUrut":6,"nama":"HARLIKA","stringJenisKelamin":"Laki-Laki"},{"namaKab":"KOTA KENDARI","originalFilename":"YUDDIN.JPG","namaPartai":"Persatuan Indonesia","id":61815,"noUrut":6,"nama":"YUDDIN, S.SI","stringJenisKelamin":"Laki-Laki"},{"namaKab":"KOTA KENDARI","originalFilename":"06 H.DJAPAR SULEMAN.jpg","namaPartai":"Partai Golongan Karya","id":74469,"noUrut":6,"nama":"Drs. H. DJAFAR SULEMAN, M.Si","stringJenisKelamin":"Laki-Laki"},{"namaKab":"KOTA KENDARI","originalFilename":"SIMON T..JPG","namaPartai":"PARTAI DEMOKRASI INDONESIA PERJUANGAN","id":134454,"noUrut":6,"nama":"SIMON TAKENDENGAN, S.tp","stringJenisKelamin":"Laki-Laki"},{"namaKab":"KOTA KENDARI","originalFilename":"la ode sabri.jpg","namaPartai":"Partai NasDem","id":167059,"noUrut":6,"nama":"LA ODE SABRI","stringJenisKelamin":"Laki-Laki"},{"namaKab":"KOTA KENDARI","originalFilename":"SAMELUDDIN.jpg","namaPartai":"Partai Hati Nurani Rakyat","id":221857,"noUrut":6,"nama":"-. SYAMELUDDIN, SH","stringJenisKelamin":"Laki-Laki"},{"namaKab":"KOTA KENDARI","originalFilename":"FOTO.jpg","namaPartai":"Partai Kebangkitan Bangsa","id":239034,"noUrut":6,"nama":"TAYEB P, SE","stringJenisKelamin":"Laki-Laki"},{"namaKab":"KOTA KENDARI","originalFilename":"3.6 la hamuda.jpg","namaPartai":"Partai Persatuan pembangunan","id":245774,"noUrut":6,"nama":"LA HAMUDA PIINO, S.Pd, M.Si","stringJenisKelamin":"Laki-Laki"}]