[{"id":30538,"idParent":30536,"namaWilayah":"AMIS","tingkatWilayah":4,"idPro":26141,"idKab":30503,"idKec":30536,"idKel":30538,"namaPro":"JAWA BARAT","namaKab":"INDRAMAYU","namaKec":"CIKEDUNG","namaKel":"AMIS","kodeWilayah":"32.12.04.2004"},{"id":30541,"idParent":30536,"namaWilayah":"CIKEDUNG","tingkatWilayah":4,"idPro":26141,"idKab":30503,"idKec":30536,"idKel":30541,"namaPro":"JAWA BARAT","namaKab":"INDRAMAYU","namaKec":"CIKEDUNG","namaKel":"CIKEDUNG","kodeWilayah":"32.12.04.2007"},{"id":30542,"idParent":30536,"namaWilayah":"CIKEDUNG LOR","tingkatWilayah":4,"idPro":26141,"idKab":30503,"idKec":30536,"idKel":30542,"namaPro":"JAWA BARAT","namaKab":"INDRAMAYU","namaKec":"CIKEDUNG","namaKel":"CIKEDUNG LOR","kodeWilayah":"32.12.04.2012"},{"id":30540,"idParent":30536,"namaWilayah":"JAMBAK","tingkatWilayah":4,"idPro":26141,"idKab":30503,"idKec":30536,"idKel":30540,"namaPro":"JAWA BARAT","namaKab":"INDRAMAYU","namaKec":"CIKEDUNG","namaKel":"JAMBAK","kodeWilayah":"32.12.04.2006"},{"id":30539,"idParent":30536,"namaWilayah":"JATISURA","tingkatWilayah":4,"idPro":26141,"idKab":30503,"idKec":30536,"idKel":30539,"namaPro":"JAWA BARAT","namaKab":"INDRAMAYU","namaKec":"CIKEDUNG","namaKel":"JATISURA","kodeWilayah":"32.12.04.2005"},{"id":30537,"idParent":30536,"namaWilayah":"LOYANG","tingkatWilayah":4,"idPro":26141,"idKab":30503,"idKec":30536,"idKel":30537,"namaPro":"JAWA BARAT","namaKab":"INDRAMAYU","namaKec":"CIKEDUNG","namaKel":"LOYANG","kodeWilayah":"32.12.04.2003"},{"id":30543,"idParent":30536,"namaWilayah":"MUNDAKJAYA","tingkatWilayah":4,"idPro":26141,"idKab":30503,"idKec":30536,"idKel":30543,"namaPro":"JAWA BARAT","namaKab":"INDRAMAYU","namaKec":"CIKEDUNG","namaKel":"MUNDAKJAYA","kodeWilayah":"32.12.04.2013"}]